Workbook
Name UPDATE: 'Data Sheet'!$E$1

Sheet Financials>>>

Sheet Historical Financial
B2: ="HISTORICAL FINANCIAL STATEMENT" & "-" & 'Data Sheet'!B1 -> HISTORICAL FINANCIAL STATEMENT-TATA CONSUMER PRODUCTS LTD
B3: YEAR | C3: ='Data Sheet'!B16 -> 42460 | D3: ='Data Sheet'!C16 -> 42825 | E3: ='Data Sheet'!D16 -> 43190 | F3: ='Data Sheet'!E16 -> 43555 | G3: ='Data Sheet'!F16 -> 43921 | H3: ='Data Sheet'!G16 -> 44286 | I3: ='Data Sheet'!H16 -> 44651 | J3: ='Data Sheet'!I16 -> 45016 | ... L3: ='Data Sheet'!K16 -> 45747 | M3: LTM
A5: # | B5: Income Statement
B6: ='Data Sheet'!A17 -> Sales | C6: =IFERROR('Data Sheet'!B17,0) -> 6636.54 | D6: =IFERROR('Data Sheet'!C17,0) -> 6779.55 | E6: =IFERROR('Data Sheet'!D17,0) -> 6815.35 | F6: =IFERROR('Data Sheet'!E17,0) -> 7251.5 | G6: =IFERROR('Data Sheet'!F17,0) -> 9637.42 | H6: =IFERROR('Data Sheet'!G17,0) -> 11602.03 | I6: =IFERROR('Data Sheet'!H17,0) -> 12425.37 | J6: =IFERROR('Data Sheet'!I17,0) -> 13783.16 | ... L6: =IFERROR('Data Sheet'!K17,0) -> 17618.3 | M6: =IFERROR(SUM('Data Sheet'!H42:K42),0) -> 19465.03
B7: Sales Growth% | C7: - | D7: =IFERROR(D6/C6-1,0) -> 0.021548879 | E7: =IFERROR(E6/D6-1,0) -> 0.0052805865 | F7: =IFERROR(F6/E6-1,0) -> 0.063995246 | G7: =IFERROR(G6/F6-1,0) -> 0.32902434 | H7: =IFERROR(H6/G6-1,0) -> 0.20385228 | I7: =IFERROR(I6/H6-1,0) -> 0.070965167 | J7: =IFERROR(J6/I6-1,0) -> 0.10927562 | K7: =IFERROR(K6/J6-1,0) -> 0.10321944 | ... M7: =IFERROR(M6/L6-1,0) -> 0.10481885
B9: Cost of Good Sold | C9: =IFERROR(SUM('Data Sheet'!B18,'Data Sheet'!B20:B22)-1*'Data Sheet'!C19,0) -> 4677.44 | D9: =IFERROR(SUM('Data Sheet'!C18,'Data Sheet'!C20:C22)-1*'Data Sheet'!C19,0) -> 4680.71 | E9: =IFERROR(SUM('Data Sheet'!D18,'Data Sheet'!D20:D22)-1*'Data Sheet'!D19,0) -> 4802.44 | F9: =IFERROR(SUM('Data Sheet'!E18,'Data Sheet'!E20:E22)-1*'Data Sheet'!E19,0) -> 5112.81 | G9: =IFERROR(SUM('Data Sheet'!F18,'Data Sheet'!F20:F22)-1*'Data Sheet'!F19,0) -> 6637.79 | H9: =IFERROR(SUM('Data Sheet'!G18,'Data Sheet'!G20:G22)-1*'Data Sheet'!G19,0) -> 8227.59 | I9: =IFERROR(SUM('Data Sheet'!H18,'Data Sheet'!H20:H22)-1*'Data Sheet'!H19,0) -> 8594.93 | J9: =IFERROR(SUM('Data Sheet'!I18,'Data Sheet'!I20:I22)-1*'Data Sheet'!I19,0) -> 9681.17 | K9: =IFERROR(SUM('Data Sheet'!J18,'Data Sheet'!J20:J22)-1*'Data Sheet'!J19,0) -> 10354.23 | L9: =IFERROR(SUM('Data Sheet'!K18,'Data Sheet'!K20:K22)-1*'Data Sheet'!K19,0) -> 12092.75 | M9: =IFERROR(SUM('Data Sheet'!H43:K43),0) -> 16844.69
B10: COGS % Sales | C10: =IFERROR(C9/C6,0) -> 0.704801 | D10: =IFERROR(D9/D6,0) -> 0.69041603 | E10: =IFERROR(E9/E6,0) -> 0.70465053 | F10: =IFERROR(F9/F6,0) -> 0.7050693 | G10: =IFERROR(G9/G6,0) -> 0.68875176 | H10: =IFERROR(H9/H6,0) -> 0.7091509 | I10: =IFERROR(I9/I6,0) -> 0.69172427 | J10: =IFERROR(J9/J6,0) -> 0.70239118 | ... M10: =IFERROR(M9/M6,0) -> 0.86538218
B12: Gross Profit | C12: =C6-C9 -> 1959.1 | D12: =D6-D9 -> 2098.84 | E12: =E6-E9 -> 2012.91 | F12: =F6-F9 -> 2138.69 | G12: =G6-G9 -> 2999.63 | H12: =H6-H9 -> 3374.44 | I12: =I6-I9 -> 3830.44 | J12: =J6-J9 -> 4101.99 | ... M12: =M6-M9 -> 2620.34
B13: Gross Margin | C13: =C12/C6 -> 0.295199 | D13: =D12/D6 -> 0.30958397 | E13: =E12/E6 -> 0.29534947 | F13: =F12/F6 -> 0.2949307 | G13: =G12/G6 -> 0.31124824 | H13: =H12/H6 -> 0.2908491 | I13: =I12/I6 -> 0.30827573 | J13: =J12/J6 -> 0.29760882 | ... M13: =M12/M6 -> 0.13461782
B15: ='Data Sheet'!A23 -> Selling and admin | C15: =IFERROR(SUM('Data Sheet'!B24),0) -> 649.51 | D15: =IFERROR(SUM('Data Sheet'!C24),0) -> 380.79 | E15: =IFERROR(SUM('Data Sheet'!D24),0) -> 316.36 | F15: =IFERROR(SUM('Data Sheet'!E24),0) -> 384.55 | G15: =IFERROR(SUM('Data Sheet'!F24),0) -> 429.32 | H15: =IFERROR(SUM('Data Sheet'!G24),0) -> 409.22 | I15: =IFERROR(SUM('Data Sheet'!H24),0) -> 419.83 | J15: =IFERROR(SUM('Data Sheet'!I24),0) -> 460.26 | ... M15: =IFERROR(SUM('Data Sheet'!L24),0) -> 0
B16: S$G Exp % Sales | C16: =IFERROR(C15/C6,0) -> 0.097868769 | D16: =IFERROR(D15/D6,0) -> 0.056167445 | E16: =IFERROR(E15/E6,0) -> 0.046418746 | F16: =IFERROR(F15/F6,0) -> 0.053030408 | G16: =IFERROR(G15/G6,0) -> 0.044547192 | H16: =IFERROR(H15/H6,0) -> 0.035271414 | I16: =IFERROR(I15/I6,0) -> 0.033788129 | J16: =IFERROR(J15/J6,0) -> 0.033392923 | ... M16: =IFERROR(M15/M6,0) -> 0
B18: EBITDA | C18: =C12-C15 -> 1309.59 | D18: =D12-D15 -> 1718.05 | E18: =E12-E15 -> 1696.55 | F18: =F12-F15 -> 1754.14 | G18: =G12-G15 -> 2570.31 | H18: =H12-H15 -> 2965.22 | I18: =I12-I15 -> 3410.61 | J18: =J12-J15 -> 3641.73 | ... L18: =L12-L15 -> 4732.72 | M18: =IFERROR(SUM('Data Sheet'!H45:K45,'Data Sheet'!H46:K46,'Data Sheet'!H48:K48),0) -> 1258.15
B19: EBITDA % Sales | C19: =IFERROR(C18/C6,0) -> 0.19733024 | D19: =IFERROR(D18/D6,0) -> 0.25341652 | E19: =IFERROR(E18/E6,0) -> 0.24893072 | F19: =IFERROR(F18/F6,0) -> 0.2419003 | G19: =IFERROR(G18/G6,0) -> 0.26670105 | H19: =IFERROR(H18/H6,0) -> 0.25557769 | I19: =IFERROR(I18/I6,0) -> 0.2744876 | J19: =IFERROR(J18/J6,0) -> 0.2642159 | ... M19: =IFERROR(M18/M6,0) -> 0.064636427
B21: ='Data Sheet'!A26 -> Depreciation | C21: =IFERROR('Data Sheet'!B26,0) -> 116.79 | D21: =IFERROR('Data Sheet'!C26,0) -> 126.04 | E21: =IFERROR('Data Sheet'!D26,0) -> 116.04 | F21: =IFERROR('Data Sheet'!E26,0) -> 122.57 | G21: =IFERROR('Data Sheet'!F26,0) -> 241.71 | H21: =IFERROR('Data Sheet'!G26,0) -> 254.74 | I21: =IFERROR('Data Sheet'!H26,0) -> 278.01 | J21: =IFERROR('Data Sheet'!I26,0) -> 304.08 | ... L21: =IFERROR('Data Sheet'!K26,0) -> 600.74 | M21: =IFERROR(SUM('Data Sheet'!H45:K45),0) -> 614.59
B22: Depreciation % Sales | C22: =C21/C6 -> 0.017598025 | D22: =D21/D6 -> 0.018591204 | E22: =E21/E6 -> 0.017026272 | F22: =F21/F6 -> 0.01690271 | G22: =G21/G6 -> 0.025080364 | H22: =H21/H6 -> 0.021956502 | I22: =I21/I6 -> 0.022374384 | J22: =J21/J6 -> 0.022061704 | ... M22: =M21/M6 -> 0.031574059
B24: ='Data Sheet'!A27 -> Interest | C24: =IFERROR('Data Sheet'!B27,0) -> 116.9 | D24: =IFERROR('Data Sheet'!C27,0) -> 91.53 | E24: =IFERROR('Data Sheet'!D27,0) -> 42.76 | F24: =IFERROR('Data Sheet'!E27,0) -> 52.47 | G24: =IFERROR('Data Sheet'!F27,0) -> 77.86 | H24: =IFERROR('Data Sheet'!G27,0) -> 68.69 | I24: =IFERROR('Data Sheet'!H27,0) -> 72.78 | J24: =IFERROR('Data Sheet'!I27,0) -> 87.16 | ... L24: =IFERROR('Data Sheet'!K27,0) -> 290.2 | M24: =IFERROR(SUM('Data Sheet'!H46:K46),0) -> 138.6
B25: Interest % Sales | C25: =C24/C6 -> 0.0176146 | D25: =D24/D6 -> 0.013500896 | E25: =E24/E6 -> 0.0062740725 | F25: =F24/F6 -> 0.0072357443 | G25: =G24/G6 -> 0.0080789257 | H25: =H24/H6 -> 0.0059205156 | I25: =I24/I6 -> 0.0058573708 | J25: =J24/J6 -> 0.0063236587 | ... M25: =M24/M6 -> 0.0071204617
B27: Earning After Tax | C27: =C18-C21-C24 -> 1075.9 | D27: =D18-D21-D24 -> 1500.48 | E27: =E18-E21-E24 -> 1537.75 | F27: =F18-F21-F24 -> 1579.1 | G27: =G18-G21-G24 -> 2250.74 | H27: =H18-H21-H24 -> 2641.79 | I27: =I18-I21-I24 -> 3059.82 | J27: =J18-J21-J24 -> 3250.49 | ... M27: =M18-M21-M24 -> 504.96
B28: EBT % Sales | C28: =C27/C6 -> 0.16211761 | D28: =D27/D6 -> 0.22132442 | E28: =E27/E6 -> 0.22563038 | F28: =F27/F6 -> 0.21776184 | G28: =G27/G6 -> 0.23354176 | H28: =H27/H6 -> 0.22770067 | I28: =I27/I6 -> 0.24625585 | J28: =J27/J6 -> 0.23583054 | ... M28: =M27/M6 -> 0.025941907
B30: Tax | C30: ='Data Sheet'!B29 -> 200.01 | D30: ='Data Sheet'!C29 -> 198.31 | E30: ='Data Sheet'!D29 -> 185.87 | F30: ='Data Sheet'!E29 -> 260.88 | G30: ='Data Sheet'!F29 -> 274.19 | H30: ='Data Sheet'!G29 -> 317.27 | I30: ='Data Sheet'!H29 -> 377.04 | J30: ='Data Sheet'!I29 -> 447.04 | ... L30: ='Data Sheet'!K29 -> 396.24 | M30: =IFERROR(SUM('Data Sheet'!H29:K29),0) -> 1615.05
B31: Tax % Sales | C31: =C30/C6 -> 0.030137692 | D31: =D30/D6 -> 0.029251204 | E31: =E30/E6 -> 0.02727226 | F31: =F30/F6 -> 0.035976005 | G31: =G30/G6 -> 0.02845056 | H31: =H30/H6 -> 0.027346077 | I31: =I30/I6 -> 0.030344368 | J31: =J30/J6 -> 0.032433782 | ... M31: =M30/M6 -> 0.082971873
B33: Net Profit | C33: =C27-C30 -> 875.89 | D33: =D27-D30 -> 1302.17 | E33: =E27-E30 -> 1351.88 | F33: =F27-F30 -> 1318.22 | G33: =G27-G30 -> 1976.55 | H33: =H27-H30 -> 2324.52 | I33: =I27-I30 -> 2682.78 | J33: =J27-J30 -> 2803.45 | ... M33: =M27-M30 -> -1110.09
B34: Net Profit % Sales | C34: =C33/C6 -> 0.13197992 | D34: =D33/D6 -> 0.19207322 | E34: =E33/E6 -> 0.19835812 | F34: =F33/F6 -> 0.18178584 | G34: =G33/G6 -> 0.2050912 | H34: =H33/H6 -> 0.20035459 | I34: =I33/I6 -> 0.21591148 | J34: =J33/J6 -> 0.20339675 | ... M34: =M33/M6 -> -0.057029966
B36: No.of Equity Share | C36: =IFERROR('Data Sheet'!B93,0) -> 65.54 | D36: =IFERROR('Data Sheet'!C93,0) -> 65.54 | E36: =IFERROR('Data Sheet'!D93,0) -> 65.54 | F36: =IFERROR('Data Sheet'!E93,0) -> 65.54 | G36: =IFERROR('Data Sheet'!F93,0) -> 95.7 | H36: =IFERROR('Data Sheet'!G93,0) -> 95.7 | I36: =IFERROR('Data Sheet'!H93,0) -> 95.7 | J36: =IFERROR('Data Sheet'!I93,0) -> 96.47 | ... L36: =IFERROR('Data Sheet'!K93,0) -> 98.95 | M36: =L36 -> 98.95
B38: EPS | C38: =IFERROR(C33/C36,0) -> 13.364205 | D38: =IFERROR(D33/D36,0) -> 19.868325 | E38: =IFERROR(E33/E36,0) -> 20.626793 | F38: =IFERROR(F33/F36,0) -> 20.113213 | G38: =IFERROR(G33/G36,0) -> 20.653605 | H38: =IFERROR(H33/H36,0) -> 24.289655 | I38: =IFERROR(I33/I36,0) -> 28.033229 | J38: =IFERROR(J33/J36,0) -> 29.06033 | ... M38: =IFERROR(M33/M36,0) -> -11.218696
B39: EPS Growth | C39: - | D39: =IFERROR(D38/C38-1,0) -> 0.48668212 | E39: =IFERROR(E38/D38-1,0) -> 0.038174739 | F39: =IFERROR(F38/E38-1,0) -> -0.02489866 | G39: =IFERROR(G38/F38-1,0) -> 0.026867498 | H39: =IFERROR(H38/G38-1,0) -> 0.17604918 | I39: =IFERROR(I38/H38-1,0) -> 0.15412214 | J39: =IFERROR(J38/I38-1,0) -> 0.036638691 | K39: =IFERROR(K38/J38-1,0) -> 0.15094329 | ... M39: =IFERROR(M38/L38-1,0) -> -1.3221817
B41: Dividend Per Share | C41: =IFERROR('Data Sheet'!B31/'Historical Financial'!C38,0) -> 10.625398 | D41: =IFERROR('Data Sheet'!C31/'Historical Financial'!D38,0) -> 7.4646455 | E41: =IFERROR('Data Sheet'!D31/'Historical Financial'!E38,0) -> 7.1901629 | F41: =IFERROR('Data Sheet'!E31/'Historical Financial'!F38,0) -> 7.8445944 | G41: =IFERROR('Data Sheet'!F31/'Historical Financial'!G38,0) -> 12.047776 | H41: =IFERROR('Data Sheet'!G31/'Historical Financial'!H38,0) -> 15.366624 | I41: =IFERROR('Data Sheet'!H31/'Historical Financial'!I38,0) -> 19.88961 | J41: =IFERROR('Data Sheet'!I31/'Historical Financial'!J38,0) -> 27.01277 | ... L41: =IFERROR('Data Sheet'!K31/'Historical Financial'!L38,0) -> 23.443885 | M41: -
B42: Dividend Pay out Ratio | C42: =C41/C38 -> 0.79506399 | D42: =D41/D38 -> 0.37570583 | E42: =E41/E38 -> 0.34858366 | F42: =F41/F38 -> 0.39002194 | G42: =G41/G38 -> 0.58332556 | H42: =H41/H38 -> 0.63264068 | I42: =I41/I38 -> 0.70950123 | J42: =J41/J38 -> 0.92954107 | ... L42: =L41/L38 -> 0.67326817 | M42: -
B44: Retain Earning | C44: =IFERROR(IF(C38>C41,C38-C41,0),0) -> 2.7388069 | D44: =IFERROR(IF(D38>D41,D38-D41,0),0) -> 12.403679 | E44: =IFERROR(IF(E38>E41,E38-E41,0),0) -> 13.43663 | F44: =IFERROR(IF(F38>F41,F38-F41,0),0) -> 12.268619 | G44: =IFERROR(IF(G38>G41,G38-G41,0),0) -> 8.6058293 | H44: =IFERROR(IF(H38>H41,H38-H41,0),0) -> 8.9230311 | I44: =IFERROR(IF(I38>I41,I38-I41,0),0) -> 8.1436184 | J44: =IFERROR(IF(J38>J41,J38-J41,0),0) -> 2.0475597 | ... M44: =IFERROR(IF(M38>M41,M38-M41,0),0) -> 0
A47: # | B47: Balance sheet
B49: ='Data Sheet'!A57 -> Equity Share Capital | C49: =IFERROR('Data Sheet'!B57,0) -> 63.11 | D49: =IFERROR('Data Sheet'!C57,0) -> 63.11 | E49: =IFERROR('Data Sheet'!D57,0) -> 63.11 | F49: =IFERROR('Data Sheet'!E57,0) -> 63.11 | G49: =IFERROR('Data Sheet'!F57,0) -> 92.16 | H49: =IFERROR('Data Sheet'!G57,0) -> 92.16 | I49: =IFERROR('Data Sheet'!H57,0) -> 92.16 | J49: =IFERROR('Data Sheet'!I57,0) -> 92.9 | ... L49: =IFERROR('Data Sheet'!K57,0) -> 98.95
B50: ='Data Sheet'!A58 -> Reserves | C50: =IFERROR('Data Sheet'!B58,0) -> 6184.06 | D50: =IFERROR('Data Sheet'!C58,0) -> 6202.39 | E50: =IFERROR('Data Sheet'!D58,0) -> 6968.49 | F50: =IFERROR('Data Sheet'!E58,0) -> 7268.58 | G50: =IFERROR('Data Sheet'!F58,0) -> 13722.7 | H50: =IFERROR('Data Sheet'!G58,0) -> 14442.35 | I50: =IFERROR('Data Sheet'!H58,0) -> 15049.78 | J50: =IFERROR('Data Sheet'!I58,0) -> 16183.81 | ... L50: =IFERROR('Data Sheet'!K58,0) -> 19902.13
B51: ='Data Sheet'!A59 -> Borrowings | C51: =IFERROR('Data Sheet'!B59,0) -> 1354.05 | D51: =IFERROR('Data Sheet'!C59,0) -> 786.56 | E51: =IFERROR('Data Sheet'!D59,0) -> 1067.58 | F51: =IFERROR('Data Sheet'!E59,0) -> 1141.1 | G51: =IFERROR('Data Sheet'!F59,0) -> 1586.32 | H51: =IFERROR('Data Sheet'!G59,0) -> 1633.55 | I51: =IFERROR('Data Sheet'!H59,0) -> 1412.01 | J51: =IFERROR('Data Sheet'!I59,0) -> 1600.04 | ... L51: =IFERROR('Data Sheet'!K59,0) -> 2392.68
B52: ='Data Sheet'!A60 -> Other Liabilities | C52: =IFERROR('Data Sheet'!B60,0) -> 2293.54 | D52: =IFERROR('Data Sheet'!C60,0) -> 2499.35 | E52: =IFERROR('Data Sheet'!D60,0) -> 2361.58 | F52: =IFERROR('Data Sheet'!E60,0) -> 2407.89 | G52: =IFERROR('Data Sheet'!F60,0) -> 3071.86 | H52: =IFERROR('Data Sheet'!G60,0) -> 4049.76 | I52: =IFERROR('Data Sheet'!H60,0) -> 4520.92 | J52: =IFERROR('Data Sheet'!I60,0) -> 4885.74 | ... L52: =IFERROR('Data Sheet'!K60,0) -> 9436.86
B53: Total Liabilities | C53: =IFERROR('Data Sheet'!B61,0) -> 9894.76 | D53: =IFERROR('Data Sheet'!C61,0) -> 9551.41 | E53: =IFERROR('Data Sheet'!D61,0) -> 10460.76 | F53: =IFERROR('Data Sheet'!E61,0) -> 10880.68 | G53: =IFERROR('Data Sheet'!F61,0) -> 18473.04 | H53: =IFERROR('Data Sheet'!G61,0) -> 20217.82 | I53: =IFERROR('Data Sheet'!H61,0) -> 21074.87 | J53: =IFERROR('Data Sheet'!I61,0) -> 22762.49 | ... L53: =IFERROR('Data Sheet'!K61,0) -> 31830.62
B55: ='Data Sheet'!A62 -> Net Block | C55: ='Data Sheet'!B62 -> 4661.8 | D55: ='Data Sheet'!C62 -> 4572.59 | E55: ='Data Sheet'!D62 -> 4798.18 | F55: ='Data Sheet'!E62 -> 4913.31 | G55: ='Data Sheet'!F62 -> 11656.04 | H55: ='Data Sheet'!G62 -> 12023.13 | I55: ='Data Sheet'!H62 -> 12599.35 | ... L55: ='Data Sheet'!K62 -> 21476.84
B56: ='Data Sheet'!A63 -> Capital Work in Progress | C56: =IFERROR('Data Sheet'!B63,0) -> 39.42 | D56: =IFERROR('Data Sheet'!C63,0) -> 63.19 | E56: =IFERROR('Data Sheet'!D63,0) -> 135.16 | F56: =IFERROR('Data Sheet'!E63,0) -> 424.41 | G56: =IFERROR('Data Sheet'!F63,0) -> 95.35 | H56: =IFERROR('Data Sheet'!G63,0) -> 112.85 | I56: =IFERROR('Data Sheet'!H63,0) -> 246.97 | J56: =IFERROR('Data Sheet'!I63,0) -> 294.9 | ... L56: =IFERROR('Data Sheet'!K63,0) -> 218.1
B57: ='Data Sheet'!A64 -> Investments | C57: =IFERROR('Data Sheet'!B64,0) -> 1365.94 | D57: =IFERROR('Data Sheet'!C64,0) -> 1451.04 | E57: =IFERROR('Data Sheet'!D64,0) -> 1161.33 | F57: =IFERROR('Data Sheet'!E64,0) -> 1187.66 | G57: =IFERROR('Data Sheet'!F64,0) -> 1322.85 | H57: =IFERROR('Data Sheet'!G64,0) -> 805.89 | I57: =IFERROR('Data Sheet'!H64,0) -> 797.28 | J57: =IFERROR('Data Sheet'!I64,0) -> 1432.97 | ... L57: =IFERROR('Data Sheet'!K64,0) -> 968.67
B58: ='Data Sheet'!A65 -> Other Assets | C58: =IFERROR('Data Sheet'!B65- SUM('Data Sheet'!B67:B69),0) -> 1105.13 | D58: =IFERROR('Data Sheet'!C65- SUM('Data Sheet'!C67:C69),0) -> 844.36 | E58: =IFERROR('Data Sheet'!D65- SUM('Data Sheet'!D67:D69),0) -> 1031.36 | F58: =IFERROR('Data Sheet'!E65- SUM('Data Sheet'!E67:E69),0) -> 1032.6 | G58: =IFERROR('Data Sheet'!F65- SUM('Data Sheet'!F67:F69),0) -> 1142.9 | H58: =IFERROR('Data Sheet'!G65- SUM('Data Sheet'!G67:G69),0) -> 1190.59 | I58: =IFERROR('Data Sheet'!H65- SUM('Data Sheet'!H67:H69),0) -> 1729.72 | J58: =IFERROR('Data Sheet'!I65- SUM('Data Sheet'!I67:I69),0) -> 1667.64 | ... L58: =IFERROR('Data Sheet'!K65- SUM('Data Sheet'!K67:K69),0) -> 1879.45
B59: Total Non- current Assets | C59: =IFERROR(SUM(C55:C58),0) -> 7172.29 | D59: =IFERROR(SUM(D55:D58),0) -> 6931.18 | E59: =IFERROR(SUM(E55:E58),0) -> 7126.03 | F59: =IFERROR(SUM(F55:F58),0) -> 7557.98 | G59: =IFERROR(SUM(G55:G58),0) -> 14217.14 | H59: =IFERROR(SUM(H55:H58),0) -> 14132.46 | I59: =IFERROR(SUM(I55:I58),0) -> 15373.32 | J59: =IFERROR(SUM(J55:J58),0) -> 16465.55 | ... L59: =IFERROR(SUM(L55:L58),0) -> 24543.06
B61: ='Data Sheet'!A67 -> Receivables | C61: =IFERROR('Data Sheet'!B67,0) -> 592.43 | D61: =IFERROR('Data Sheet'!C67,0) -> 592.45 | E61: =IFERROR('Data Sheet'!D67,0) -> 648.28 | F61: =IFERROR('Data Sheet'!E67,0) -> 680.55 | G61: =IFERROR('Data Sheet'!F67,0) -> 922.41 | H61: =IFERROR('Data Sheet'!G67,0) -> 761.32 | I61: =IFERROR('Data Sheet'!H67,0) -> 835.15 | J61: =IFERROR('Data Sheet'!I67,0) -> 798.33 | ... L61: =IFERROR('Data Sheet'!K67,0) -> 869.79
B62: ='Data Sheet'!A68 -> Inventory | C62: =IFERROR('Data Sheet'!B68,0) -> 1629.01 | D62: =IFERROR('Data Sheet'!C68,0) -> 1452.96 | E62: =IFERROR('Data Sheet'!D68,0) -> 1448.31 | F62: =IFERROR('Data Sheet'!E68,0) -> 1608.54 | G62: =IFERROR('Data Sheet'!F68,0) -> 1712.03 | H62: =IFERROR('Data Sheet'!G68,0) -> 2249.16 | I62: =IFERROR('Data Sheet'!H68,0) -> 2266.51 | J62: =IFERROR('Data Sheet'!I68,0) -> 2701.67 | ... L62: =IFERROR('Data Sheet'!K68,0) -> 3599.91
B63: ='Data Sheet'!A69 -> Cash & Bank | C63: =IFERROR('Data Sheet'!B69,0) -> 501.03 | D63: =IFERROR('Data Sheet'!C69,0) -> 574.82 | E63: =IFERROR('Data Sheet'!D69,0) -> 1238.14 | F63: =IFERROR('Data Sheet'!E69,0) -> 1033.61 | G63: =IFERROR('Data Sheet'!F69,0) -> 1621.46 | H63: =IFERROR('Data Sheet'!G69,0) -> 3074.88 | I63: =IFERROR('Data Sheet'!H69,0) -> 2599.89 | J63: =IFERROR('Data Sheet'!I69,0) -> 2796.94 | ... L63: =IFERROR('Data Sheet'!K69,0) -> 2817.86
B64: Total Current Assets | C64: =IFERROR(SUM(C61:C63),0) -> 2722.47 | D64: =IFERROR(SUM(D61:D63),0) -> 2620.23 | E64: =IFERROR(SUM(E61:E63),0) -> 3334.73 | F64: =IFERROR(SUM(F61:F63),0) -> 3322.7 | G64: =IFERROR(SUM(G61:G63),0) -> 4255.9 | H64: =IFERROR(SUM(H61:H63),0) -> 6085.36 | I64: =IFERROR(SUM(I61:I63),0) -> 5701.55 | J64: =IFERROR(SUM(J61:J63),0) -> 6296.94 | ... L64: =IFERROR(SUM(L61:L63),0) -> 7287.56
B66: Total Assest | C66: =SUM(C59,C64) -> 9894.76 | D66: =SUM(D59,D64) -> 9551.41 | E66: =SUM(E59,E64) -> 10460.76 | F66: =SUM(F59,F64) -> 10880.68 | G66: =SUM(G59,G64) -> 18473.04 | H66: =SUM(H59,H64) -> 20217.82 | I66: =SUM(I59,I64) -> 21074.87 | J66: =SUM(J59,J64) -> 22762.49 | ... L66: =SUM(L59,L64) -> 31830.62
B68: Check | C68: =IF(C53=C66,TRUE, FALSE) -> TRUE | D68: =IF(D53=D66,TRUE, FALSE) -> TRUE | E68: =IF(E53=E66,TRUE, FALSE) -> TRUE | F68: =IF(F53=F66,TRUE, FALSE) -> TRUE | G68: =IF(G53=G66,TRUE, FALSE) -> TRUE | H68: =IF(H53=H66,TRUE, FALSE) -> TRUE | I68: =IF(I53=I66,TRUE, FALSE) -> TRUE | J68: =IF(J53=J66,TRUE, FALSE) -> TRUE | ... L68: =IF(L53=L66,TRUE, FALSE) -> TRUE
C69: =C53-C66 -> 0 | D69: =D53-D66 -> 0 | E69: =E53-E66 -> 0 | F69: =F53-F66 -> 0 | G69: =G53-G66 -> 0 | H69: =H53-H66 -> 0 | I69: =I53-I66 -> 0 | J69: =J53-J66 -> 0 | ... L69: =L53-L66 -> 0
A92: # | B92: CashFlow Statement
B94: Operating Activity
B95: ='Cashflow Data '!B4 -> Profit from operations | C95: ='Cashflow Data '!C4 -> 650 | D95: ='Cashflow Data '!D4 -> 803 | E95: ='Cashflow Data '!E4 -> 794 | F95: ='Cashflow Data '!F4 -> 799 | G95: ='Cashflow Data '!G4 -> 1293 | H95: ='Cashflow Data '!H4 -> 1579 | I95: ='Cashflow Data '!I4 -> 1749 | ... L95: ='Cashflow Data '!L4 -> 2514
B96: ='Cashflow Data '!B5 -> Receivables | C96: ='Cashflow Data '!C5 -> -48 | D96: ='Cashflow Data '!D5 -> -60 | E96: ='Cashflow Data '!E5 -> -114 | F96: ='Cashflow Data '!F5 -> -133 | G96: ='Cashflow Data '!G5 -> -177 | H96: ='Cashflow Data '!H5 -> 186 | I96: ='Cashflow Data '!I5 -> -149 | ... L96: ='Cashflow Data '!L5 -> 36
B97: ='Cashflow Data '!B6 -> Inventory | C97: ='Cashflow Data '!C6 -> -70 | D97: ='Cashflow Data '!D6 -> 158 | E97: ='Cashflow Data '!E6 -> -13 | F97: ='Cashflow Data '!F6 -> -156 | G97: ='Cashflow Data '!G6 -> 81 | H97: ='Cashflow Data '!H6 -> -533 | I97: ='Cashflow Data '!I6 -> -1 | ... L97: ='Cashflow Data '!L6 -> -734
B98: ='Cashflow Data '!B7 -> Payables | C98: ='Cashflow Data '!C7 -> -153 | D98: ='Cashflow Data '!D7 -> 51 | E98: ='Cashflow Data '!E7 -> -12 | F98: ='Cashflow Data '!F7 -> -133 | G98: ='Cashflow Data '!G7 -> 14 | H98: ='Cashflow Data '!H7 -> 531 | I98: ='Cashflow Data '!I7 -> 152 | ... L98: ='Cashflow Data '!L7 -> 704
B99: ='Cashflow Data '!B8 -> Working capital changes | C99: ='Cashflow Data '!C8 -> -272 | D99: ='Cashflow Data '!D8 -> 148 | E99: ='Cashflow Data '!E8 -> -139 | F99: ='Cashflow Data '!F8 -> -422 | G99: ='Cashflow Data '!G8 -> -82 | H99: ='Cashflow Data '!H8 -> 183 | I99: ='Cashflow Data '!I8 -> 2 | ... L99: ='Cashflow Data '!L8 -> 5
B100: ='Cashflow Data '!B9 -> Direct taxes | C100: ='Cashflow Data '!C9 -> -234 | D100: ='Cashflow Data '!D9 -> -211 | E100: ='Cashflow Data '!E9 -> -299 | F100: ='Cashflow Data '!F9 -> -167 | G100: ='Cashflow Data '!G9 -> -128 | H100: ='Cashflow Data '!H9 -> -106 | I100: ='Cashflow Data '!I9 -> -235 | ... L100: ='Cashflow Data '!L9 -> -462
B101: ='Cashflow Data '!B10 -> Other operating items | C101: ='Cashflow Data '!C10 -> -28 | D101: ='Cashflow Data '!D10 -> 0 | E101: ='Cashflow Data '!E10 -> 0 | F101: ='Cashflow Data '!F10 -> 0 | G101: ='Cashflow Data '!G10 -> 0 | H101: ='Cashflow Data '!H10 -> 0 | I101: ='Cashflow Data '!I10 -> 0 | ... L101: ='Cashflow Data '!L10 -> 0
B102: Cash from Operating Activity | C102: =C95+C100+C101+C99 -> 116 | D102: =D95+D100+D101+D99 -> 740 | E102: =E95+E100+E101+E99 -> 356 | F102: =F95+F100+F101+F99 -> 210 | G102: =G95+G100+G101+G99 -> 1083 | H102: =H95+H100+H101+H99 -> 1656 | I102: =I95+I100+I101+I99 -> 1516 | J102: =J95+J100+J101+J99 -> 1461 | ... L102: =L95+L100+L101+L99 -> 2057
B104: Investment Activity
B105: Fixed assets purchased | C105: ='Cashflow Data '!C12 -> -154 | D105: ='Cashflow Data '!D12 -> -138 | E105: ='Cashflow Data '!E12 -> -359 | F105: ='Cashflow Data '!F12 -> -282 | G105: ='Cashflow Data '!G12 -> -160 | H105: ='Cashflow Data '!H12 -> -211 | I105: ='Cashflow Data '!I12 -> -273 | J105: ='Cashflow Data '!J12 -> -312 | ... L105: ='Cashflow Data '!L12 -> -460
B106: Fixed assets sold | C106: ='Cashflow Data '!C13 -> 8 | D106: ='Cashflow Data '!D13 -> 6 | E106: ='Cashflow Data '!E13 -> 9 | F106: ='Cashflow Data '!F13 -> 26 | G106: ='Cashflow Data '!G13 -> 9 | H106: ='Cashflow Data '!H13 -> 32 | I106: ='Cashflow Data '!I13 -> 27 | J106: ='Cashflow Data '!J13 -> 172 | ... L106: ='Cashflow Data '!L13 -> 45
B107: Investments purchased | C107: ='Cashflow Data '!C14 -> 0 | D107: ='Cashflow Data '!D14 -> 0 | E107: ='Cashflow Data '!E14 -> -372 | F107: ='Cashflow Data '!F14 -> 0 | G107: ='Cashflow Data '!G14 -> -222 | H107: ='Cashflow Data '!H14 -> 0 | I107: ='Cashflow Data '!I14 -> 0 | J107: ='Cashflow Data '!J14 -> -533 | ... L107: ='Cashflow Data '!L14 -> -29
B108: Investments sold | C108: ='Cashflow Data '!C15 -> 175 | D108: ='Cashflow Data '!D15 -> 14 | E108: ='Cashflow Data '!E15 -> 811 | F108: ='Cashflow Data '!F15 -> 26 | G108: ='Cashflow Data '!G15 -> 65 | H108: ='Cashflow Data '!H15 -> 523 | I108: ='Cashflow Data '!I15 -> 136 | J108: ='Cashflow Data '!J15 -> 4 | ... L108: ='Cashflow Data '!L15 -> 0
B109: Investment income | C109: ='Cashflow Data '!C16 -> 0 | D109: ='Cashflow Data '!D16 -> 0 | E109: ='Cashflow Data '!E16 -> 0 | F109: ='Cashflow Data '!F16 -> 0 | G109: ='Cashflow Data '!G16 -> 0 | H109: ='Cashflow Data '!H16 -> 0 | I109: ='Cashflow Data '!I16 -> 0 | J109: ='Cashflow Data '!J16 -> 0 | ... L109: ='Cashflow Data '!L16 -> 0
B110: Interest received | C110: ='Cashflow Data '!C17 -> 17 | D110: ='Cashflow Data '!D17 -> 29 | E110: ='Cashflow Data '!E17 -> 33 | F110: ='Cashflow Data '!F17 -> 49 | G110: ='Cashflow Data '!G17 -> 51 | H110: ='Cashflow Data '!H17 -> 68 | I110: ='Cashflow Data '!I17 -> 75 | J110: ='Cashflow Data '!J17 -> 109 | ... L110: ='Cashflow Data '!L17 -> 111
B111: Dividends received | C111: ='Cashflow Data '!C18 -> 53 | D111: ='Cashflow Data '!D18 -> 29 | E111: ='Cashflow Data '!E18 -> 16 | F111: ='Cashflow Data '!F18 -> 5 | G111: ='Cashflow Data '!G18 -> 5 | H111: ='Cashflow Data '!H18 -> 5 | I111: ='Cashflow Data '!I18 -> 13 | J111: ='Cashflow Data '!J18 -> 13 | ... L111: ='Cashflow Data '!L18 -> 7
B112: Invest in subsidiaries | C112: ='Cashflow Data '!C19 -> 0 | D112: ='Cashflow Data '!D19 -> 0 | E112: ='Cashflow Data '!E19 -> 0 | F112: ='Cashflow Data '!F19 -> 0 | G112: ='Cashflow Data '!G19 -> 0 | H112: ='Cashflow Data '!H19 -> 0 | I112: ='Cashflow Data '!I19 -> 0 | J112: ='Cashflow Data '!J19 -> 0 | ... L112: ='Cashflow Data '!L19 -> 0
B113: Investment in group cos | C113: ='Cashflow Data '!C20 -> -51 | D113: ='Cashflow Data '!D20 -> -28 | E113: ='Cashflow Data '!E20 -> -13 | F113: ='Cashflow Data '!F20 -> -36 | G113: ='Cashflow Data '!G20 -> -53 | H113: ='Cashflow Data '!H20 -> -112 | I113: ='Cashflow Data '!I20 -> -236 | J113: ='Cashflow Data '!J20 -> -150 | ... L113: ='Cashflow Data '!L20 -> -125
B114: Redemp n Canc of Shares | C114: ='Cashflow Data '!C21 -> 0 | D114: ='Cashflow Data '!D21 -> 0 | E114: ='Cashflow Data '!E21 -> 51 | F114: ='Cashflow Data '!F21 -> 0 | G114: ='Cashflow Data '!G21 -> 30 | H114: ='Cashflow Data '!H21 -> 57 | I114: ='Cashflow Data '!I21 -> 11 | J114: ='Cashflow Data '!J21 -> 9 | ... L114: ='Cashflow Data '!L21 -> 0
B115: Acquisition of companies | C115: ='Cashflow Data '!C22 -> 0 | D115: ='Cashflow Data '!D22 -> 0 | E115: ='Cashflow Data '!E22 -> 0 | F115: ='Cashflow Data '!F22 -> 0 | G115: ='Cashflow Data '!G22 -> 0 | H115: ='Cashflow Data '!H22 -> -169 | I115: ='Cashflow Data '!I22 -> -511 | J115: ='Cashflow Data '!J22 -> -55 | ... L115: ='Cashflow Data '!L22 -> -1809
B116: Inter corporate deposits | C116: ='Cashflow Data '!C23 -> 73 | D116: ='Cashflow Data '!D23 -> 313 | E116: ='Cashflow Data '!E23 -> 44 | F116: ='Cashflow Data '!F23 -> 44 | G116: ='Cashflow Data '!G23 -> 132 | H116: ='Cashflow Data '!H23 -> -73 | I116: ='Cashflow Data '!I23 -> -499 | J116: ='Cashflow Data '!J23 -> 70 | ... L116: ='Cashflow Data '!L23 -> -144
B117: Other investing items | C117: ='Cashflow Data '!C24 -> 24 | D117: ='Cashflow Data '!D24 -> -79 | E117: ='Cashflow Data '!E24 -> -250 | F117: ='Cashflow Data '!F24 -> 222 | G117: ='Cashflow Data '!G24 -> -481 | H117: ='Cashflow Data '!H24 -> -467 | I117: ='Cashflow Data '!I24 -> -61 | J117: ='Cashflow Data '!J24 -> -160 | ... L117: ='Cashflow Data '!L24 -> 99
B118: Cash from Investing Activity | C118: =SUM(C105:C117) -> 145 | D118: =SUM(D105:D117) -> 146 | E118: =SUM(E105:E117) -> -30 | F118: =SUM(F105:F117) -> 54 | G118: =SUM(G105:G117) -> -624 | H118: =SUM(H105:H117) -> -347 | I118: =SUM(I105:I117) -> -1318 | J118: =SUM(J105:J117) -> -833 | ... L118: =SUM(L105:L117) -> -2305
B120: Financing Activity
B121: Proceeds from shares | C121: ='Cashflow Data '!C26 -> 0 | D121: ='Cashflow Data '!D26 -> 0 | E121: ='Cashflow Data '!E26 -> 0 | F121: ='Cashflow Data '!F26 -> 0 | G121: ='Cashflow Data '!G26 -> 0 | H121: ='Cashflow Data '!H26 -> 0 | I121: ='Cashflow Data '!I26 -> 0 | J121: ='Cashflow Data '!J26 -> 0 | ... L121: ='Cashflow Data '!L26 -> 2981
B122: Proceeds from debentures | C122: ='Cashflow Data '!C27 -> 0 | D122: ='Cashflow Data '!D27 -> 0 | E122: ='Cashflow Data '!E27 -> 0 | F122: ='Cashflow Data '!F27 -> 0 | G122: ='Cashflow Data '!G27 -> 0 | H122: ='Cashflow Data '!H27 -> 0 | I122: ='Cashflow Data '!I27 -> 0 | J122: ='Cashflow Data '!J27 -> 0 | ... L122: ='Cashflow Data '!L27 -> 0
B123: Redemption of debentures | C123: ='Cashflow Data '!C28 -> 0 | D123: ='Cashflow Data '!D28 -> -398 | E123: ='Cashflow Data '!E28 -> 0 | F123: ='Cashflow Data '!F28 -> 0 | G123: ='Cashflow Data '!G28 -> 0 | H123: ='Cashflow Data '!H28 -> 0 | I123: ='Cashflow Data '!I28 -> 0 | J123: ='Cashflow Data '!J28 -> 0 | ... L123: ='Cashflow Data '!L28 -> 0
B124: Proceeds from borrowings | C124: ='Cashflow Data '!C29 -> 0 | D124: ='Cashflow Data '!D29 -> 0 | E124: ='Cashflow Data '!E29 -> 216 | F124: ='Cashflow Data '!F29 -> 101 | G124: ='Cashflow Data '!G29 -> 50 | H124: ='Cashflow Data '!H29 -> 12 | I124: ='Cashflow Data '!I29 -> 0 | J124: ='Cashflow Data '!J29 -> 53 | ... L124: ='Cashflow Data '!L29 -> 60
B125: Repayment of borrowings | C125: ='Cashflow Data '!C30 -> -80 | D125: ='Cashflow Data '!D30 -> -87 | E125: ='Cashflow Data '!E30 -> 0 | F125: ='Cashflow Data '!F30 -> -65 | G125: ='Cashflow Data '!G30 -> -18 | H125: ='Cashflow Data '!H30 -> -69 | I125: ='Cashflow Data '!I30 -> -495 | J125: ='Cashflow Data '!J30 -> -56 | ... L125: ='Cashflow Data '!L30 -> -1511
B126: Interest paid fin | C126: ='Cashflow Data '!C31 -> -66 | D126: ='Cashflow Data '!D31 -> -61 | E126: ='Cashflow Data '!E31 -> -28 | F126: ='Cashflow Data '!F31 -> -44 | G126: ='Cashflow Data '!G31 -> -70 | H126: ='Cashflow Data '!H31 -> -65 | I126: ='Cashflow Data '!I31 -> -63 | J126: ='Cashflow Data '!J31 -> -82 | ... L126: ='Cashflow Data '!L31 -> -261
B127: Dividends paid | C127: ='Cashflow Data '!C32 -> -187 | D127: ='Cashflow Data '!D32 -> -189 | E127: ='Cashflow Data '!E32 -> -212 | F127: ='Cashflow Data '!F32 -> -216 | G127: ='Cashflow Data '!G32 -> -222 | H127: ='Cashflow Data '!H32 -> -267 | I127: ='Cashflow Data '!I32 -> -398 | J127: ='Cashflow Data '!J32 -> -573 | ... L127: ='Cashflow Data '!L32 -> -741
B128: Financial liabilities | C128: ='Cashflow Data '!C33 -> 0 | D128: ='Cashflow Data '!D33 -> 0 | E128: ='Cashflow Data '!E33 -> 0 | F128: ='Cashflow Data '!F33 -> 0 | G128: ='Cashflow Data '!G33 -> -49 | H128: ='Cashflow Data '!H33 -> -45 | I128: ='Cashflow Data '!I33 -> -53 | J128: ='Cashflow Data '!J33 -> -56 | ... L128: ='Cashflow Data '!L33 -> -75
B129: Other financing items | C129: ='Cashflow Data '!C34 -> 51 | D129: ='Cashflow Data '!D34 -> -81 | E129: ='Cashflow Data '!E34 -> -6 | F129: ='Cashflow Data '!F34 -> 0 | G129: ='Cashflow Data '!G34 -> 0 | H129: ='Cashflow Data '!H34 -> 9 | I129: ='Cashflow Data '!I34 -> 13 | J129: ='Cashflow Data '!J34 -> 0 | ... L129: ='Cashflow Data '!L34 -> 0
B130: Cash from Financing Activity | C130: =SUM(C121:C129) -> -282 | D130: =SUM(D121:D129) -> -816 | E130: =SUM(E121:E129) -> -30 | F130: =SUM(F121:F129) -> -224 | G130: =SUM(G121:G129) -> -309 | H130: =SUM(H121:H129) -> -425 | I130: =SUM(I121:I129) -> -996 | J130: =SUM(J121:J129) -> -714 | ... L130: =SUM(L121:L129) -> 453
B132: Net Cash Flow | C132: =IFERROR(SUM(C102,C118,C130),0) -> -21 | D132: =IFERROR(SUM(D102,D118,D130),0) -> 70 | E132: =IFERROR(SUM(E102,E118,E130),0) -> 296 | F132: =IFERROR(SUM(F102,F118,F130),0) -> 40 | G132: =IFERROR(SUM(G102,G118,G130),0) -> 150 | H132: =IFERROR(SUM(H102,H118,H130),0) -> 884 | I132: =IFERROR(SUM(I102,I118,I130),0) -> -798 | J132: =IFERROR(SUM(J102,J118,J130),0) -> -86 | ... L132: =IFERROR(SUM(L102,L118,L130),0) -> 205

Sheet Ratio Analysis
B2: ="Ratio Analysis" & "-" & 'Data Sheet'!B1 -> Ratio Analysis-TATA CONSUMER PRODUCTS LTD
B3: Particular | C3: ='Data Sheet'!B16 -> 42460 | D3: ='Data Sheet'!C16 -> 42825 | E3: ='Data Sheet'!D16 -> 43190 | F3: ='Data Sheet'!E16 -> 43555 | G3: ='Data Sheet'!F16 -> 43921 | H3: ='Data Sheet'!G16 -> 44286 | I3: ='Data Sheet'!H16 -> 44651 | J3: ='Data Sheet'!I16 -> 45016 | ... L3: ='Data Sheet'!K16 -> 45747 | M3: Trend | N3: Mean | O3: Median
B5: Sales Growth | C5: - | D5: =IFERROR('Historical Financial'!D7,0) -> 0.021548879 | E5: =IFERROR('Historical Financial'!E7,0) -> 0.0052805865 | F5: =IFERROR('Historical Financial'!F7,0) -> 0.063995246 | G5: =IFERROR('Historical Financial'!G7,0) -> 0.32902434 | H5: =IFERROR('Historical Financial'!H7,0) -> 0.20385228 | I5: =IFERROR('Historical Financial'!I7,0) -> 0.070965167 | J5: =IFERROR('Historical Financial'!J7,0) -> 0.10927562 | K5: =IFERROR('Historical Financial'!K7,0) -> 0.10321944 | L5: =IFERROR('Historical Financial'!L7,0) -> 0.15865276 | N5: =AVERAGE(C5:L5) -> 0.11842381 | O5: =MEDIAN(C5:L5) -> 0.10321944
B6: EBITDA Growth | C6: - | D6: =IFERROR('Historical Financial'!D19/'Historical Financial'!C19-1,0) -> 0.28422552 | E6: =IFERROR('Historical Financial'!E19/'Historical Financial'!D19-1,0) -> -0.017701301 | F6: =IFERROR('Historical Financial'!F19/'Historical Financial'!E19-1,0) -> -0.028242501 | G6: =IFERROR('Historical Financial'!G19/'Historical Financial'!F19-1,0) -> 0.10252468 | H6: =IFERROR('Historical Financial'!H19/'Historical Financial'!G19-1,0) -> -0.041707219 | I6: =IFERROR('Historical Financial'!I19/'Historical Financial'!H19-1,0) -> 0.073988904 | J6: =IFERROR('Historical Financial'!J19/'Historical Financial'!I19-1,0) -> -0.037421372 | K6: =IFERROR('Historical Financial'!K19/'Historical Financial'!J19-1,0) -> 0.048193291 | L6: =IFERROR('Historical Financial'!L19/'Historical Financial'!K19-1,0) -> -0.030056385 | N6: =AVERAGE(C6:L6) -> 0.039311513 | O6: =MEDIAN(C6:L6) -> -0.017701301
B7: EBIT Growth | C7: - | D7: =IFERROR('Historical Financial'!D28/'Historical Financial'!C28-1,0) -> 0.36520903 | E7: =IFERROR('Historical Financial'!E28/'Historical Financial'!D28-1,0) -> 0.019455396 | F7: =IFERROR('Historical Financial'!F28/'Historical Financial'!E28-1,0) -> -0.034873567 | G7: =IFERROR('Historical Financial'!G28/'Historical Financial'!F28-1,0) -> 0.072464094 | H7: =IFERROR('Historical Financial'!H28/'Historical Financial'!G28-1,0) -> -0.025010891 | I7: =IFERROR('Historical Financial'!I28/'Historical Financial'!H28-1,0) -> 0.081489336 | J7: =IFERROR('Historical Financial'!J28/'Historical Financial'!I28-1,0) -> -0.042335282 | K7: =IFERROR('Historical Financial'!K28/'Historical Financial'!J28-1,0) -> 0.032985536 | L7: =IFERROR('Historical Financial'!L28/'Historical Financial'!K28-1,0) -> -0.10489453 | N7: =AVERAGE(C7:L7) -> 0.040498792 | O7: =MEDIAN(C7:L7) -> 0.019455396
B8: Net Profit Growth | C8: - | D8: =IFERROR('Historical Financial'!D33/'Historical Financial'!C33-1,0) -> 0.48668212 | E8: =IFERROR('Historical Financial'!E33/'Historical Financial'!D33-1,0) -> 0.038174739 | F8: =IFERROR('Historical Financial'!F33/'Historical Financial'!E33-1,0) -> -0.02489866 | G8: =IFERROR('Historical Financial'!G33/'Historical Financial'!F33-1,0) -> 0.49940829 | H8: =IFERROR('Historical Financial'!H33/'Historical Financial'!G33-1,0) -> 0.17604918 | I8: =IFERROR('Historical Financial'!I33/'Historical Financial'!H33-1,0) -> 0.15412214 | J8: =IFERROR('Historical Financial'!J33/'Historical Financial'!I33-1,0) -> 0.044979462 | K8: =IFERROR('Historical Financial'!K33/'Historical Financial'!J33-1,0) -> 0.18053113 | L8: =IFERROR('Historical Financial'!L33/'Historical Financial'!K33-1,0) -> 0.041087033 | N8: =AVERAGE(C8:L8) -> 0.17734838 | O8: =MEDIAN(C8:L8) -> 0.15412214
B9: Dividend Growth | C9: - | D9: =IFERROR('Historical Financial'!D41/'Historical Financial'!C41-1,0) -> -0.29747146 | E9: =IFERROR('Historical Financial'!E41/'Historical Financial'!D41-1,0) -> -0.036771015 | F9: =IFERROR('Historical Financial'!F41/'Historical Financial'!E41-1,0) -> 0.091017617 | G9: =IFERROR('Historical Financial'!G41/'Historical Financial'!F41-1,0) -> 0.53580607 | H9: =IFERROR('Historical Financial'!H41/'Historical Financial'!G41-1,0) -> 0.27547395 | I9: =IFERROR('Historical Financial'!I41/'Historical Financial'!H41-1,0) -> 0.29433832 | J9: =IFERROR('Historical Financial'!J41/'Historical Financial'!I41-1,0) -> 0.3581347 | K9: =IFERROR('Historical Financial'!K41/'Historical Financial'!J41-1,0) -> -0.18270307 | L9: =IFERROR('Historical Financial'!L41/'Historical Financial'!K41-1,0) -> 0.061892587 | N9: =AVERAGE(C9:L9) -> 0.12219086 | O9: =MEDIAN(C9:L9) -> 0.091017617
B11: Gross Margin | C11: =IFERROR('Historical Financial'!C13,0) -> 0.295199 | D11: =IFERROR('Historical Financial'!D13,0) -> 0.30958397 | E11: =IFERROR('Historical Financial'!E13,0) -> 0.29534947 | F11: =IFERROR('Historical Financial'!F13,0) -> 0.2949307 | G11: =IFERROR('Historical Financial'!G13,0) -> 0.31124824 | H11: =IFERROR('Historical Financial'!H13,0) -> 0.2908491 | I11: =IFERROR('Historical Financial'!I13,0) -> 0.30827573 | J11: =IFERROR('Historical Financial'!J13,0) -> 0.29760882 | ... L11: =IFERROR('Historical Financial'!L13,0) -> 0.31362561 | N11: =AVERAGE(C11:L11) -> 0.30357334 | O11: =MEDIAN(C11:L11) -> 0.30294228
B12: EBITDA Margin | C12: =IFERROR('Historical Financial'!C19,0) -> 0.19733024 | D12: =IFERROR('Historical Financial'!D19,0) -> 0.25341652 | E12: =IFERROR('Historical Financial'!E19,0) -> 0.24893072 | F12: =IFERROR('Historical Financial'!F19,0) -> 0.2419003 | G12: =IFERROR('Historical Financial'!G19,0) -> 0.26670105 | H12: =IFERROR('Historical Financial'!H19,0) -> 0.25557769 | I12: =IFERROR('Historical Financial'!I19,0) -> 0.2744876 | J12: =IFERROR('Historical Financial'!J19,0) -> 0.2642159 | ... L12: =IFERROR('Historical Financial'!L19,0) -> 0.26862524 | N12: =AVERAGE(C12:L12) -> 0.25481346 | O12: =MEDIAN(C12:L12) -> 0.25989679
B13: EBIT Margin | C13: =IFERROR(('Historical Financial'!C18-'Historical Financial'!C21)/'Historical Financial'!C6,0) -> 0.17973221 | D13: =IFERROR(('Historical Financial'!D18-'Historical Financial'!D21)/'Historical Financial'!D6,0) -> 0.23482532 | E13: =IFERROR(('Historical Financial'!E18-'Historical Financial'!E21)/'Historical Financial'!E6,0) -> 0.23190445 | F13: =IFERROR(('Historical Financial'!F18-'Historical Financial'!F21)/'Historical Financial'!F6,0) -> 0.22499759 | G13: =IFERROR(('Historical Financial'!G18-'Historical Financial'!G21)/'Historical Financial'!G6,0) -> 0.24162068 | H13: =IFERROR(('Historical Financial'!H18-'Historical Financial'!H21)/'Historical Financial'!H6,0) -> 0.23362119 | I13: =IFERROR(('Historical Financial'!I18-'Historical Financial'!I21)/'Historical Financial'!I6,0) -> 0.25211322 | J13: =IFERROR(('Historical Financial'!J18-'Historical Financial'!J21)/'Historical Financial'!J6,0) -> 0.24215419 | ... L13: =IFERROR(('Historical Financial'!L18-'Historical Financial'!L21)/'Historical Financial'!L6,0) -> 0.23452774 | N13: =AVERAGE(C13:L13) -> 0.2327643 | O13: =MEDIAN(C13:L13) -> 0.23467653
B14: Ebt Margin | C14: =IFERROR('Historical Financial'!C28,0) -> 0.16211761 | D14: =IFERROR('Historical Financial'!D28,0) -> 0.22132442 | E14: =IFERROR('Historical Financial'!E28,0) -> 0.22563038 | F14: =IFERROR('Historical Financial'!F28,0) -> 0.21776184 | G14: =IFERROR('Historical Financial'!G28,0) -> 0.23354176 | H14: =IFERROR('Historical Financial'!H28,0) -> 0.22770067 | I14: =IFERROR('Historical Financial'!I28,0) -> 0.24625585 | J14: =IFERROR('Historical Financial'!J28,0) -> 0.23583054 | ... L14: =IFERROR('Historical Financial'!L28,0) -> 0.21805623 | N14: =AVERAGE(C14:L14) -> 0.22318288 | O14: =MEDIAN(C14:L14) -> 0.22666552
B15: Net Profit Margin | C15: =IFERROR('Historical Financial'!C34,0) -> 0.13197992 | D15: =IFERROR('Historical Financial'!D34,0) -> 0.19207322 | E15: =IFERROR('Historical Financial'!E34,0) -> 0.19835812 | F15: =IFERROR('Historical Financial'!F34,0) -> 0.18178584 | G15: =IFERROR('Historical Financial'!G34,0) -> 0.2050912 | H15: =IFERROR('Historical Financial'!H34,0) -> 0.20035459 | I15: =IFERROR('Historical Financial'!I34,0) -> 0.21591148 | J15: =IFERROR('Historical Financial'!J34,0) -> 0.20339675 | ... L15: =IFERROR('Historical Financial'!L34,0) -> 0.19556597 | N15: =AVERAGE(C15:L15) -> 0.19421675 | O15: =MEDIAN(C15:L15) -> 0.19935636
B17: Sales Expenses% sales | C17: =IFERROR('Historical Financial'!C10,0) -> 0.704801 | D17: =IFERROR('Historical Financial'!D10,0) -> 0.69041603 | E17: =IFERROR('Historical Financial'!E10,0) -> 0.70465053 | F17: =IFERROR('Historical Financial'!F10,0) -> 0.7050693 | G17: =IFERROR('Historical Financial'!G10,0) -> 0.68875176 | H17: =IFERROR('Historical Financial'!H10,0) -> 0.7091509 | I17: =IFERROR('Historical Financial'!I10,0) -> 0.69172427 | J17: =IFERROR('Historical Financial'!J10,0) -> 0.70239118 | ... L17: =IFERROR('Historical Financial'!L10,0) -> 0.68637439 | N17: =AVERAGE(C17:L17) -> 0.69642666 | O17: =MEDIAN(C17:L17) -> 0.69705772
B18: Depreciation % Sales | C18: =IFERROR('Historical Financial'!C22,0) -> 0.017598025 | D18: =IFERROR('Historical Financial'!D22,0) -> 0.018591204 | E18: =IFERROR('Historical Financial'!E22,0) -> 0.017026272 | F18: =IFERROR('Historical Financial'!F22,0) -> 0.01690271 | G18: =IFERROR('Historical Financial'!G22,0) -> 0.025080364 | H18: =IFERROR('Historical Financial'!H22,0) -> 0.021956502 | I18: =IFERROR('Historical Financial'!I22,0) -> 0.022374384 | J18: =IFERROR('Historical Financial'!J22,0) -> 0.022061704 | ... L18: =IFERROR('Historical Financial'!L22,0) -> 0.034097501 | N18: =AVERAGE(C18:L18) -> 0.022049162 | O18: =MEDIAN(C18:L18) -> 0.022009103
B19: OperatingIncome%Sales | C19: =C13 -> 0.17973221 | D19: =D13 -> 0.23482532 | E19: =E13 -> 0.23190445 | F19: =F13 -> 0.22499759 | G19: =G13 -> 0.24162068 | H19: =H13 -> 0.23362119 | I19: =I13 -> 0.25211322 | J19: =J13 -> 0.24215419 | ... L19: =L13 -> 0.23452774 | N19: =AVERAGE(C19:L19) -> 0.2327643 | O19: =MEDIAN(C19:L19) -> 0.23467653
B21: Return On Capital Employed | C21: =IFERROR(('Historical Financial'!C18-'Historical Financial'!C21)/SUM('Historical Financial'!C49:C51),0) -> 0.15692218 | D21: =IFERROR(('Historical Financial'!D18-'Historical Financial'!D21)/SUM('Historical Financial'!D49:D51),0) -> 0.22575106 | E21: =IFERROR(('Historical Financial'!E18-'Historical Financial'!E21)/SUM('Historical Financial'!E49:E51),0) -> 0.19514445 | F21: =IFERROR(('Historical Financial'!F18-'Historical Financial'!F21)/SUM('Historical Financial'!F49:F51),0) -> 0.19256585 | G21: =IFERROR(('Historical Financial'!G18-'Historical Financial'!G21)/SUM('Historical Financial'!G49:G51),0) -> 0.15119621 | H21: =IFERROR(('Historical Financial'!H18-'Historical Financial'!H21)/SUM('Historical Financial'!H49:H51),0) -> 0.16764411 | I21: =IFERROR(('Historical Financial'!I18-'Historical Financial'!I21)/SUM('Historical Financial'!I49:I51),0) -> 0.1892358 | J21: =IFERROR(('Historical Financial'!J18-'Historical Financial'!J21)/SUM('Historical Financial'!J49:J51),0) -> 0.1867034 | ... L21: =IFERROR(('Historical Financial'!L18-'Historical Financial'!L21)/SUM('Historical Financial'!L49:L51),0) -> 0.18451479 | N21: =AVERAGE(C21:L21) -> 0.1845956 | O21: =MEDIAN(C21:L21) -> 0.1879696
B22: Reatained Earnings% | C22: =IFERROR('Historical Financial'!C44/'Historical Financial'!C38,0) -> 0.20493601 | D22: =IFERROR('Historical Financial'!D44/'Historical Financial'!D38,0) -> 0.62429417 | E22: =IFERROR('Historical Financial'!E44/'Historical Financial'!E38,0) -> 0.65141634 | F22: =IFERROR('Historical Financial'!F44/'Historical Financial'!F38,0) -> 0.60997806 | G22: =IFERROR('Historical Financial'!G44/'Historical Financial'!G38,0) -> 0.41667444 | H22: =IFERROR('Historical Financial'!H44/'Historical Financial'!H38,0) -> 0.36735932 | I22: =IFERROR('Historical Financial'!I44/'Historical Financial'!I38,0) -> 0.29049877 | J22: =IFERROR('Historical Financial'!J44/'Historical Financial'!J38,0) -> 0.070458927 | ... L22: =IFERROR('Historical Financial'!L44/'Historical Financial'!L38,0) -> 0.32673183 | N22: =AVERAGE(C22:L22) -> 0.3902271 | O22: =MEDIAN(C22:L22) -> 0.35364121
B23: Return on Equity% | C23: =IFERROR('Historical Financial'!C33/SUM('Historical Financial'!C49:C50),0) -> 0.14020589 | D23: =IFERROR('Historical Financial'!D33/SUM('Historical Financial'!D49:D50),0) -> 0.20783178 | E23: =IFERROR('Historical Financial'!E33/SUM('Historical Financial'!E49:E50),0) -> 0.19225781 | F23: =IFERROR('Historical Financial'!F33/SUM('Historical Financial'!F49:F50),0) -> 0.17979756 | G23: =IFERROR('Historical Financial'!G33/SUM('Historical Financial'!G49:G50),0) -> 0.1430742 | H23: =IFERROR('Historical Financial'!H33/SUM('Historical Financial'!H49:H50),0) -> 0.15993109 | I23: =IFERROR('Historical Financial'!I33/SUM('Historical Financial'!I49:I50),0) -> 0.17717545 | J23: =IFERROR('Historical Financial'!J33/SUM('Historical Financial'!J49:J50),0) -> 0.1722369 | ... L23: =IFERROR('Historical Financial'!L33/SUM('Historical Financial'!L49:L50),0) -> 0.1722677 | N23: =AVERAGE(C23:L23) -> 0.17508943 | O23: =MEDIAN(C23:L23) -> 0.17472157
B24: Self Sustained Growth Rate | C24: =IFERROR(C22*C23,0) -> 0.028733235 | D24: =IFERROR(D22*D23,0) -> 0.12974817 | E24: =IFERROR(E22*E23,0) -> 0.12523988 | F24: =IFERROR(F22*F23,0) -> 0.10967257 | G24: =IFERROR(G22*G23,0) -> 0.059615361 | H24: =IFERROR(H22*H23,0) -> 0.058752175 | I24: =IFERROR(I22*I23,0) -> 0.051469249 | J24: =IFERROR(J22*J23,0) -> 0.012135627 | ... L24: =IFERROR(L22*L23,0) -> 0.05628534 | N24: =AVERAGE(C24:L24) -> 0.070171516 | O24: =MEDIAN(C24:L24) -> 0.059183768
B25: Interest Coverage Ratio | C25: =IFERROR(('Historical Financial'!C18-'Historical Financial'!C21)/'Historical Financial'!C24,0) -> 10.203593 | D25: =IFERROR(('Historical Financial'!D18-'Historical Financial'!D21)/'Historical Financial'!D24,0) -> 17.393314 | E25: =IFERROR(('Historical Financial'!E18-'Historical Financial'!E21)/'Historical Financial'!E24,0) -> 36.962348 | F25: =IFERROR(('Historical Financial'!F18-'Historical Financial'!F21)/'Historical Financial'!F24,0) -> 31.095293 | G25: =IFERROR(('Historical Financial'!G18-'Historical Financial'!G21)/'Historical Financial'!G24,0) -> 29.907526 | H25: =IFERROR(('Historical Financial'!H18-'Historical Financial'!H21)/'Historical Financial'!H24,0) -> 39.459601 | I25: =IFERROR(('Historical Financial'!I18-'Historical Financial'!I21)/'Historical Financial'!I24,0) -> 43.042045 | J25: =IFERROR(('Historical Financial'!J18-'Historical Financial'!J21)/'Historical Financial'!J24,0) -> 38.293369 | ... L25: =IFERROR(('Historical Financial'!L18-'Historical Financial'!L21)/'Historical Financial'!L24,0) -> 14.238387 | N25: =AVERAGE(C25:L25) -> 29.013172 | O25: =MEDIAN(C25:L25) -> 30.501409
B27: Debtor Turnover Ratio | C27: =IFERROR('Historical Financial'!C6/'Historical Financial'!C61,0) -> 11.202235 | D27: =IFERROR('Historical Financial'!D6/'Historical Financial'!D61,0) -> 11.443244 | E27: =IFERROR('Historical Financial'!E6/'Historical Financial'!E61,0) -> 10.512973 | F27: =IFERROR('Historical Financial'!F6/'Historical Financial'!F61,0) -> 10.655352 | G27: =IFERROR('Historical Financial'!G6/'Historical Financial'!G61,0) -> 10.448087 | H27: =IFERROR('Historical Financial'!H6/'Historical Financial'!H61,0) -> 15.239361 | I27: =IFERROR('Historical Financial'!I6/'Historical Financial'!I61,0) -> 14.87801 | J27: =IFERROR('Historical Financial'!J6/'Historical Financial'!J61,0) -> 17.264991 | ... L27: =IFERROR('Historical Financial'!L6/'Historical Financial'!L61,0) -> 20.255809 | N27: =AVERAGE(C27:L27) -> 13.885668 | O27: =MEDIAN(C27:L27) -> 13.160627
B28: Creditor Turnover Ratio | C28: =IFERROR('Historical Financial'!C6/'Historical Financial'!C52,0) -> 2.8935794 | D28: =IFERROR('Historical Financial'!D6/'Historical Financial'!D52,0) -> 2.7125253 | E28: =IFERROR('Historical Financial'!E6/'Historical Financial'!E52,0) -> 2.8859281 | F28: =IFERROR('Historical Financial'!F6/'Historical Financial'!F52,0) -> 3.0115578 | G28: =IFERROR('Historical Financial'!G6/'Historical Financial'!G52,0) -> 3.137324 | H28: =IFERROR('Historical Financial'!H6/'Historical Financial'!H52,0) -> 2.8648685 | I28: =IFERROR('Historical Financial'!I6/'Historical Financial'!I52,0) -> 2.7484163 | J28: =IFERROR('Historical Financial'!J6/'Historical Financial'!J52,0) -> 2.8210998 | ... L28: =IFERROR('Historical Financial'!L6/'Historical Financial'!L52,0) -> 1.8669663 | N28: =AVERAGE(C28:L28) -> 2.6764464 | O28: =MEDIAN(C28:L28) -> 2.8429842
B29: Inventory Turnover Ratio | C29: =IFERROR('Historical Financial'!C6/'Historical Financial'!C62,0) -> 4.0739713 | D29: =IFERROR('Historical Financial'!D6/'Historical Financial'!D62,0) -> 4.6660266 | E29: =IFERROR('Historical Financial'!E6/'Historical Financial'!E62,0) -> 4.705726 | F29: =IFERROR('Historical Financial'!F6/'Historical Financial'!F62,0) -> 4.5081254 | G29: =IFERROR('Historical Financial'!G6/'Historical Financial'!G62,0) -> 5.6292355 | H29: =IFERROR('Historical Financial'!H6/'Historical Financial'!H62,0) -> 5.1583836 | I29: =IFERROR('Historical Financial'!I6/'Historical Financial'!I62,0) -> 5.4821598 | J29: =IFERROR('Historical Financial'!J6/'Historical Financial'!J62,0) -> 5.1017186 | ... L29: =IFERROR('Historical Financial'!L6/'Historical Financial'!L62,0) -> 4.8940946 | N29: =AVERAGE(C29:L29) -> 4.9710206 | O29: =MEDIAN(C29:L29) -> 4.9979066
B30: Fixed Assest Turnover | C30: =IFERROR('Historical Financial'!C6/'Historical Financial'!C55,0) -> 1.4236003 | D30: =IFERROR('Historical Financial'!D6/'Historical Financial'!D55,0) -> 1.4826499 | E30: =IFERROR('Historical Financial'!E6/'Historical Financial'!E55,0) -> 1.4204032 | F30: =IFERROR('Historical Financial'!F6/'Historical Financial'!F55,0) -> 1.475889 | G30: =IFERROR('Historical Financial'!G6/'Historical Financial'!G55,0) -> 0.82681768 | H30: =IFERROR('Historical Financial'!H6/'Historical Financial'!H55,0) -> 0.96497584 | I30: =IFERROR('Historical Financial'!I6/'Historical Financial'!I55,0) -> 0.98619135 | J30: =IFERROR('Historical Financial'!J6/'Historical Financial'!J55,0) -> 1.0545614 | ... L30: =IFERROR('Historical Financial'!L6/'Historical Financial'!L55,0) -> 0.82033949 | N30: =AVERAGE(C30:L30) -> 1.1240939 | O30: =MEDIAN(C30:L30) -> 1.0203764
B31: Capital Turnover Ratio | C31: =IFERROR('Historical Financial'!C6/SUM('Historical Financial'!C49:C50),0) -> 1.0623274 | D31: =IFERROR('Historical Financial'!D6/SUM('Historical Financial'!D49:D50),0) -> 1.0820445 | E31: =IFERROR('Historical Financial'!E6/SUM('Historical Financial'!E49:E50),0) -> 0.96924598 | F31: =IFERROR('Historical Financial'!F6/SUM('Historical Financial'!F49:F50),0) -> 0.98906255 | G31: =IFERROR('Historical Financial'!G6/SUM('Historical Financial'!G49:G50),0) -> 0.69761257 | H31: =IFERROR('Historical Financial'!H6/SUM('Historical Financial'!H49:H50),0) -> 0.79824019 | I31: =IFERROR('Historical Financial'!I6/SUM('Historical Financial'!I49:I50),0) -> 0.820593 | J31: =IFERROR('Historical Financial'!J6/SUM('Historical Financial'!J49:J50),0) -> 0.84680258 | ... L31: =IFERROR('Historical Financial'!L6/SUM('Historical Financial'!L49:L50),0) -> 0.88086743 | N31: =AVERAGE(C31:L31) -> 0.90938006 | O31: =MEDIAN(C31:L31) -> 0.91393589
B33: Debtors Days | C33: =IFERROR(365/C27,0) -> 32.582784 | D33: =IFERROR(365/D27,0) -> 31.896549 | E33: =IFERROR(365/E27,0) -> 34.719009 | F33: =IFERROR(365/F27,0) -> 34.255085 | G33: =IFERROR(365/G27,0) -> 34.934625 | H33: =IFERROR(365/H27,0) -> 23.951136 | I33: =IFERROR(365/I27,0) -> 24.532851 | J33: =IFERROR(365/J27,0) -> 21.141048 | ... L33: =IFERROR(365/L27,0) -> 18.019522 | N33: =AVERAGE(C33:L33) -> 27.755812 | O33: =MEDIAN(C33:L33) -> 28.2147
B34: Payable Days | C34: =IFERROR(365/C28,0) -> 126.14135 | D34: =IFERROR(365/D28,0) -> 134.56096 | E34: =IFERROR(365/E28,0) -> 126.47578 | F34: =IFERROR(365/F28,0) -> 121.19973 | G34: =IFERROR(365/G28,0) -> 116.34119 | H34: =IFERROR(365/H28,0) -> 127.4055 | I34: =IFERROR(365/I28,0) -> 132.80376 | J34: =IFERROR(365/J28,0) -> 129.38217 | ... L34: =IFERROR(365/L28,0) -> 195.50433 | N34: =AVERAGE(C34:L34) -> 141.01222 | O34: =MEDIAN(C34:L34) -> 128.39383
B35: Investory Days | C35: =IFERROR(365/C29,0) -> 89.593169 | D35: =IFERROR(365/D29,0) -> 78.225015 | E35: =IFERROR(365/E29,0) -> 77.565077 | F35: =IFERROR(365/F29,0) -> 80.964918 | G35: =IFERROR(365/G29,0) -> 64.840066 | H35: =IFERROR(365/H29,0) -> 70.7586 | I35: =IFERROR(365/I29,0) -> 66.579599 | J35: =IFERROR(365/J29,0) -> 71.544519 | ... L35: =IFERROR(365/L29,0) -> 74.579679 | N35: =AVERAGE(C35:L35) -> 74.11259 | O35: =MEDIAN(C35:L35) -> 73.062099
B36: Cash Conversion Cycle | C36: =IFERROR(SUM(C33,C35)-C34,0) -> -3.9653946 | D36: =IFERROR(SUM(D33,D35)-D34,0) -> -24.439395 | E36: =IFERROR(SUM(E33,E35)-E34,0) -> -14.191692 | F36: =IFERROR(SUM(F33,F35)-F34,0) -> -5.9797283 | G36: =IFERROR(SUM(G33,G35)-G34,0) -> -16.566498 | H36: =IFERROR(SUM(H33,H35)-H34,0) -> -32.695761 | I36: =IFERROR(SUM(I33,I35)-I34,0) -> -41.691306 | J36: =IFERROR(SUM(J33,J35)-J34,0) -> -36.696599 | ... L36: =IFERROR(SUM(L33,L35)-L34,0) -> -102.90513 | N36: =AVERAGE(C36:L36) -> -39.143816 | O36: =MEDIAN(C36:L36) -> -28.567578
B38: CFO/Sales | C38: =IFERROR('Historical Financial'!C102/'Historical Financial'!C6,0) -> 0.017478988 | D38: =IFERROR('Historical Financial'!D102/'Historical Financial'!D6,0) -> 0.10915179 | E38: =IFERROR('Historical Financial'!E102/'Historical Financial'!E6,0) -> 0.052235028 | F38: =IFERROR('Historical Financial'!F102/'Historical Financial'!F6,0) -> 0.028959526 | G38: =IFERROR('Historical Financial'!G102/'Historical Financial'!G6,0) -> 0.11237447 | H38: =IFERROR('Historical Financial'!H102/'Historical Financial'!H6,0) -> 0.14273364 | I38: =IFERROR('Historical Financial'!I102/'Historical Financial'!I6,0) -> 0.12200844 | J38: =IFERROR('Historical Financial'!J102/'Historical Financial'!J6,0) -> 0.10599891 | ... L38: =IFERROR('Historical Financial'!L102/'Historical Financial'!L6,0) -> 0.1167536 | N38: =AVERAGE(C38:L38) -> 0.093501382 | O38: =MEDIAN(C38:L38) -> 0.11076313
B39: CFO/Total Assets | C39: =IFERROR('Historical Financial'!C102/'Historical Financial'!C66,0) -> 0.011723377 | D39: =IFERROR('Historical Financial'!D102/'Historical Financial'!D66,0) -> 0.077475472 | E39: =IFERROR('Historical Financial'!E102/'Historical Financial'!E66,0) -> 0.034031944 | F39: =IFERROR('Historical Financial'!F102/'Historical Financial'!F66,0) -> 0.019300264 | G39: =IFERROR('Historical Financial'!G102/'Historical Financial'!G66,0) -> 0.058625976 | H39: =IFERROR('Historical Financial'!H102/'Historical Financial'!H66,0) -> 0.081907941 | I39: =IFERROR('Historical Financial'!I102/'Historical Financial'!I66,0) -> 0.071934014 | J39: =IFERROR('Historical Financial'!J102/'Historical Financial'!J66,0) -> 0.064184542 | ... L39: =IFERROR('Historical Financial'!L102/'Historical Financial'!L66,0) -> 0.064623309 | N39: =AVERAGE(C39:L39) -> 0.055325031 | O39: =MEDIAN(C39:L39) -> 0.064403926
B40: CFO/Total Debt | C40: =IFERROR('Historical Financial'!C102/'Historical Financial'!C51,0) -> 0.085668919 | D40: =IFERROR('Historical Financial'!D102/'Historical Financial'!D51,0) -> 0.94080553 | E40: =IFERROR('Historical Financial'!E102/'Historical Financial'!E51,0) -> 0.33346447 | F40: =IFERROR('Historical Financial'!F102/'Historical Financial'!F51,0) -> 0.18403295 | G40: =IFERROR('Historical Financial'!G102/'Historical Financial'!G51,0) -> 0.68271219 | H40: =IFERROR('Historical Financial'!H102/'Historical Financial'!H51,0) -> 1.0137431 | I40: =IFERROR('Historical Financial'!I102/'Historical Financial'!I51,0) -> 1.0736468 | J40: =IFERROR('Historical Financial'!J102/'Historical Financial'!J51,0) -> 0.91310217 | ... L40: =IFERROR('Historical Financial'!L102/'Historical Financial'!L51,0) -> 0.85970543 | N40: =AVERAGE(C40:L40) -> 0.66436481 | O40: =MEDIAN(C40:L40) -> 0.77120881

Sheet Forcasting 
B2: Sales Forcasting - Tata Consumer Products | G2: EBITDA Forcasting - Tata Consumer Products | L2: EPS Forcasting - Tata Consumer Products
B3: Year Weight | C3: Year | D3: Sales | E3: Sales Growth | G3: Year Weight | H3: Year | I3: EBITBA | J3: EBITDA Growth | L3: Year Weight | M3: Year | N3: EPS | O3: EPS Growth
B4: 1 | C4: ='Historical Financial'!$C$3 -> 42460 | D4: ='Historical Financial'!$C$6 -> 6636.54 | E4: - | G4: 1 | H4: ='Historical Financial'!$C$3 -> 42460 | I4: ='Historical Financial'!C18 -> 1309.59 | J4: - | L4: 1 | M4: ='Historical Financial'!$C$3 -> 42460 | N4: ='Historical Financial'!C38 -> 13.364205 | O4: -
B5: =B4+1 -> 2 | C5: =365+C4 -> 42825 | D5: ='Historical Financial'!$D$6 -> 6779.55 | E5: =D5/D4 -> 1.0215489 | G5: =G4+1 -> 2 | H5: =365+H4 -> 42825 | I5: ='Historical Financial'!D18 -> 1718.05 | J5: =I5/I4 -> 1.3118991 | L5: =L4+1 -> 2 | M5: =365+M4 -> 42825 | N5: ='Historical Financial'!D38 -> 19.868325 | O5: =N5/N4 -> 1.4866821
B6: =B5+1 -> 3 | C6: =365+C5 -> 43190 | D6: ='Historical Financial'!$E$6 -> 6815.35 | E6: =D6/D5 -> 1.0052806 | G6: =G5+1 -> 3 | H6: =365+H5 -> 43190 | I6: ='Historical Financial'!E18 -> 1696.55 | J6: =I6/I5 -> 0.98748581 | L6: =L5+1 -> 3 | M6: =365+M5 -> 43190 | N6: ='Historical Financial'!E38 -> 20.626793 | O6: =N6/N5 -> 1.0381747
B7: =B6+1 -> 4 | C7: =365+C6 -> 43555 | D7: ='Historical Financial'!$F$6 -> 7251.5 | E7: =D7/D6 -> 1.0639952 | G7: =G6+1 -> 4 | H7: =365+H6 -> 43555 | I7: ='Historical Financial'!F18 -> 1754.14 | J7: =I7/I6 -> 1.0339454 | L7: =L6+1 -> 4 | M7: =365+M6 -> 43555 | N7: ='Historical Financial'!F38 -> 20.113213 | O7: =N7/N6 -> 0.97510134
B8: =B7+1 -> 5 | C8: =365+C7 -> 43920 | D8: ='Historical Financial'!$G$6 -> 9637.42 | E8: =D8/D7 -> 1.3290243 | G8: =G7+1 -> 5 | H8: =365+H7 -> 43920 | I8: ='Historical Financial'!G18 -> 2570.31 | J8: =I8/I7 -> 1.4652821 | L8: =L7+1 -> 5 | M8: =365+M7 -> 43920 | N8: ='Historical Financial'!G38 -> 20.653605 | O8: =N8/N7 -> 1.0268675
B9: =B8+1 -> 6 | C9: =365+C8 -> 44285 | D9: ='Historical Financial'!$H$6 -> 11602.03 | E9: =D9/D8 -> 1.2038523 | G9: =G8+1 -> 6 | H9: =365+H8 -> 44285 | I9: ='Historical Financial'!H18 -> 2965.22 | J9: =I9/I8 -> 1.1536429 | L9: =L8+1 -> 6 | M9: =365+M8 -> 44285 | N9: ='Historical Financial'!H38 -> 24.289655 | O9: =N9/N8 -> 1.1760492
B10: =B9+1 -> 7 | C10: =365+C9 -> 44650 | D10: ='Historical Financial'!$I$6 -> 12425.37 | E10: =D10/D9 -> 1.0709652 | G10: =G9+1 -> 7 | H10: =365+H9 -> 44650 | I10: ='Historical Financial'!I18 -> 3410.61 | J10: =I10/I9 -> 1.1502047 | L10: =L9+1 -> 7 | M10: =365+M9 -> 44650 | N10: ='Historical Financial'!I38 -> 28.033229 | O10: =N10/N9 -> 1.1541221
B11: =B10+1 -> 8 | C11: =365+C10 -> 45015 | D11: ='Historical Financial'!$J$6 -> 13783.16 | E11: =D11/D10 -> 1.1092756 | G11: =G10+1 -> 8 | H11: =365+H10 -> 45015 | I11: ='Historical Financial'!J18 -> 3641.73 | J11: =I11/I10 -> 1.067765 | L11: =L10+1 -> 8 | M11: =365+M10 -> 45015 | N11: ='Historical Financial'!J38 -> 29.06033 | O11: =N11/N10 -> 1.0366387
B12: =B11+1 -> 9 | C12: =365+C11 -> 45380 | D12: ='Historical Financial'!$K$6 -> 15205.85 | E12: =D12/D11 -> 1.1032194 | G12: =G11+1 -> 9 | H12: =365+H11 -> 45380 | I12: ='Historical Financial'!K18 -> 4211.25 | J12: =I12/I11 -> 1.1563872 | L12: =L11+1 -> 9 | M12: =365+M11 -> 45380 | N12: ='Historical Financial'!K38 -> 33.446791 | O12: =N12/N11 -> 1.1509433
B13: =B12+1 -> 10 | C13: =365+C12 -> 45745 | D13: ='Historical Financial'!$L$6 -> 17618.3 | E13: =D13/D12 -> 1.1586528 | G13: =G12+1 -> 10 | H13: =365+H12 -> 45745 | I13: ='Historical Financial'!L18 -> 4732.72 | J13: =I13/I12 -> 1.1238278 | L13: =L12+1 -> 10 | M13: =365+M12 -> 45745 | N13: ='Historical Financial'!L38 -> 34.821021 | O13: =N13/N12 -> 1.041087
B14: =B13+1 -> 11 | C14: =365+C13 -> 46110 | D14: =FORECAST(B14,$D$4:$D$13,$B$4:$B$13) -> 17780.347 | E14: =D14/D13 -> 1.0091977 | G14: =G13+1 -> 11 | H14: =365+H13 -> 46110 | I14: =FORECAST(G14,$I$4:$I$13,$G$4:$G$13) -> 4912.71 | J14: =I14/I13 -> 1.038031 | L14: =L13+1 -> 11 | M14: =365+M13 -> 46110 | N14: =FORECAST(L14,$N$4:$N$13,$L$4:$L$13) -> 36.351863 | O14: =N14/N13 -> 1.0439632
B15: =B14+1 -> 12 | C15: =365+C14 -> 46475 | D15: =FORECAST(B15,$D$4:$D$13,$B$4:$B$13) -> 19053.955 | E15: =D15/D14 -> 1.0716301 | G15: =G14+1 -> 12 | H15: =365+H14 -> 46475 | I15: =FORECAST(G15,$I$4:$I$13,$G$4:$G$13) -> 5296.6542 | J15: =I15/I14 -> 1.0781532 | L15: =L14+1 -> 12 | M15: =365+M14 -> 46475 | N15: =FORECAST(L15,$N$4:$N$13,$L$4:$L$13) -> 38.51989 | O15: =N15/N14 -> 1.05964
B16: =B15+1 -> 13 | C16: =365+C15 -> 46840 | D16: =FORECAST(B16,$D$4:$D$13,$B$4:$B$13) -> 20327.562 | E16: =D16/D15 -> 1.0668422 | G16: =G15+1 -> 13 | H16: =365+H15 -> 46840 | I16: =FORECAST(G16,$I$4:$I$13,$G$4:$G$13) -> 5680.5984 | J16: =I16/I15 -> 1.0724881 | L16: =L15+1 -> 13 | M16: =365+M15 -> 46840 | N16: =FORECAST(L16,$N$4:$N$13,$L$4:$L$13) -> 40.687916 | O16: =N16/N15 -> 1.0562833
B17: =B16+1 -> 14 | C17: =365+C16 -> 47205 | D17: =FORECAST(B17,$D$4:$D$13,$B$4:$B$13) -> 21601.169 | E17: =D17/D16 -> 1.0626542 | G17: =G16+1 -> 14 | H17: =365+H16 -> 47205 | I17: =FORECAST(G17,$I$4:$I$13,$G$4:$G$13) -> 6064.5425 | J17: =I17/I16 -> 1.0675887 | L17: =L16+1 -> 14 | M17: =365+M16 -> 47205 | N17: =FORECAST(L17,$N$4:$N$13,$L$4:$L$13) -> 42.855943 | O17: =N17/N16 -> 1.0532843
B18: =B17+1 -> 15 | C18: =365+C17 -> 47570 | D18: =FORECAST(B18,$D$4:$D$13,$B$4:$B$13) -> 22874.777 | E18: =D18/D17 -> 1.0589601 | G18: =G17+1 -> 15 | H18: =365+H17 -> 47570 | I18: =FORECAST(G18,$I$4:$I$13,$G$4:$G$13) -> 6448.4867 | J18: =I18/I17 -> 1.0633097 | L18: =L17+1 -> 15 | M18: =365+M17 -> 47570 | N18: =FORECAST(L18,$N$4:$N$13,$L$4:$L$13) -> 45.023969 | O18: =N18/N17 -> 1.0505887

Sheet Comman Size 
B2: ="Comman Size Income Statement" & "-" & 'Data Sheet'!B1 -> Comman Size Income Statement-TATA CONSUMER PRODUCTS LTD
B4: Particulars | D4: ='Historical Financial'!C$3 -> 42460 | E4: ='Historical Financial'!D$3 -> 42825 | F4: ='Historical Financial'!E$3 -> 43190 | G4: ='Historical Financial'!F$3 -> 43555 | H4: ='Historical Financial'!G$3 -> 43921 | I4: ='Historical Financial'!H$3 -> 44286 | J4: ='Historical Financial'!I$3 -> 44651 | K4: ='Historical Financial'!J$3 -> 45016 | ... M4: ='Historical Financial'!L$3 -> 45747
B6: ='Data Sheet'!A17 -> Sales | D6: ='Data Sheet'!B17/'Data Sheet'!B17 -> 1 | E6: ='Data Sheet'!C17/'Data Sheet'!C17 -> 1 | F6: ='Data Sheet'!D17/'Data Sheet'!D17 -> 1 | G6: ='Data Sheet'!E17/'Data Sheet'!E17 -> 1 | H6: ='Data Sheet'!F17/'Data Sheet'!F17 -> 1 | I6: ='Data Sheet'!G17/'Data Sheet'!G17 -> 1 | J6: ='Data Sheet'!H17/'Data Sheet'!H17 -> 1 | K6: ='Data Sheet'!I17/'Data Sheet'!I17 -> 1 | ... M6: ='Data Sheet'!K17/'Data Sheet'!K17 -> 1
B7: ='Data Sheet'!A18 -> Raw Material Cost | D7: ='Data Sheet'!B18/'Data Sheet'!B17 -> 0.54267585 | E7: ='Data Sheet'!C18/'Data Sheet'!C17 -> 0.46694102 | F7: ='Data Sheet'!D18/'Data Sheet'!D17 -> 0.54965776 | G7: ='Data Sheet'!E18/'Data Sheet'!E17 -> 0.55465076 | H7: ='Data Sheet'!F18/'Data Sheet'!F17 -> 0.56061685 | I7: ='Data Sheet'!G18/'Data Sheet'!G17 -> 0.54885136 | J7: ='Data Sheet'!H18/'Data Sheet'!H17 -> 0.50889591 | K7: ='Data Sheet'!I18/'Data Sheet'!I17 -> 0.51563357 | ... M7: ='Data Sheet'!K18/'Data Sheet'!K17 -> 0.51007645
B8: ='Data Sheet'!A19 -> Change in Inventory | D8: ='Data Sheet'!B19/'Data Sheet'!B17 -> -0.0030301934 | E8: ='Data Sheet'!C19/'Data Sheet'!C17 -> 0.00010177667 | F8: ='Data Sheet'!D19/'Data Sheet'!D17 -> 0.006866852 | G8: ='Data Sheet'!E19/'Data Sheet'!E17 -> 0.0019871751 | H8: ='Data Sheet'!F19/'Data Sheet'!F17 -> -0.00080727 | I8: ='Data Sheet'!G19/'Data Sheet'!G17 -> 0.012889124 | J8: ='Data Sheet'!H19/'Data Sheet'!H17 -> 0.0032015143 | K8: ='Data Sheet'!I19/'Data Sheet'!I17 -> 0.019870625 | ... M8: ='Data Sheet'!K19/'Data Sheet'!K17 -> 0.02057463
B9: ='Data Sheet'!A20 -> Power and Fuel | D9: ='Data Sheet'!B20/'Data Sheet'!B17 -> 0.012244332 | E9: ='Data Sheet'!C20/'Data Sheet'!C17 -> 0.012270726 | F9: ='Data Sheet'!D20/'Data Sheet'!D17 -> 0.012775573 | G9: ='Data Sheet'!E20/'Data Sheet'!E17 -> 0.012311935 | H9: ='Data Sheet'!F20/'Data Sheet'!F17 -> 0.010774668 | I9: ='Data Sheet'!G20/'Data Sheet'!G17 -> 0.0083916349 | J9: ='Data Sheet'!H20/'Data Sheet'!H17 -> 0.009971534 | K9: ='Data Sheet'!I20/'Data Sheet'!I17 -> 0.010841491 | ... M9: ='Data Sheet'!K20/'Data Sheet'!K17 -> 0.0088663492
B10: ='Data Sheet'!A21 -> Other Mfr. Exp | D10: ='Data Sheet'!B21/'Data Sheet'!B17 -> 0.028677594 | E10: ='Data Sheet'!C21/'Data Sheet'!C17 -> 0.088148918 | F10: ='Data Sheet'!D21/'Data Sheet'!D17 -> 0.028566398 | G10: ='Data Sheet'!E21/'Data Sheet'!E17 -> 0.028902986 | H10: ='Data Sheet'!F21/'Data Sheet'!F17 -> 0.024744174 | I10: ='Data Sheet'!G21/'Data Sheet'!G17 -> 0.08117114 | J10: ='Data Sheet'!H21/'Data Sheet'!H17 -> 0.091714774 | K10: ='Data Sheet'!I21/'Data Sheet'!I17 -> 0.11450204 | ... M10: ='Data Sheet'!K21/'Data Sheet'!K17 -> 0.10683494
B11: ='Data Sheet'!A22 -> Employee Cost | D11: ='Data Sheet'!B22/'Data Sheet'!$B$17 -> 0.12130719 | E11: ='Data Sheet'!C22/'Data Sheet'!C17 -> 0.12315714 | F11: ='Data Sheet'!D22/'Data Sheet'!D17 -> 0.12051765 | G11: ='Data Sheet'!E22/'Data Sheet'!E17 -> 0.11119079 | H11: ='Data Sheet'!F22/'Data Sheet'!F17 -> 0.091808804 | I11: ='Data Sheet'!G22/'Data Sheet'!G17 -> 0.083625883 | J11: ='Data Sheet'!H22/'Data Sheet'!H17 -> 0.084343565 | K11: ='Data Sheet'!I22/'Data Sheet'!I17 -> 0.081284698 | L11: ='Data Sheet'!J22/'Data Sheet'!J17 -> 0.082770118 | M11: ='Data Sheet'!K22/'Data Sheet'!K17 -> 0.081171282
B12: ='Data Sheet'!A23 -> Selling and admin | D12: ='Data Sheet'!B23/'Data Sheet'!B$17 -> 0.13906041 | E12: ='Data Sheet'!C23/'Data Sheet'!C$17 -> 0.13672294 | F12: ='Data Sheet'!D23/'Data Sheet'!D$17 -> 0.12583947 | G12: ='Data Sheet'!E23/'Data Sheet'!E$17 -> 0.13352134 | H12: ='Data Sheet'!F23/'Data Sheet'!F$17 -> 0.13262471 | I12: ='Data Sheet'!G23/'Data Sheet'!G$17 -> 0.12251821 | J12: ='Data Sheet'!H23/'Data Sheet'!H$17 -> 0.13615933 | K12: ='Data Sheet'!I23/'Data Sheet'!I$17 -> 0.12952472 | ... M12: ='Data Sheet'!K23/'Data Sheet'!K$17 -> 0.1278994
B13: ='Data Sheet'!A24 -> Other Expenses | D13: ='Data Sheet'!B24/'Data Sheet'!B$17 -> 0.097868769 | E13: ='Data Sheet'!C24/'Data Sheet'!C$17 -> 0.056167445 | F13: ='Data Sheet'!D24/'Data Sheet'!D$17 -> 0.046418746 | G13: ='Data Sheet'!E24/'Data Sheet'!E$17 -> 0.053030408 | H13: ='Data Sheet'!F24/'Data Sheet'!F$17 -> 0.044547192 | I13: ='Data Sheet'!G24/'Data Sheet'!G$17 -> 0.035271414 | J13: ='Data Sheet'!H24/'Data Sheet'!H$17 -> 0.033788129 | K13: ='Data Sheet'!I24/'Data Sheet'!I$17 -> 0.033392923 | ... M13: ='Data Sheet'!K24/'Data Sheet'!K$17 -> 0.045000369
B14: ='Data Sheet'!A25 -> Other Income | D14: ='Data Sheet'!B25/'Data Sheet'!B$17 -> 0.005656562 | E14: ='Data Sheet'!C25/'Data Sheet'!C$17 -> 0.013039214 | F14: ='Data Sheet'!D25/'Data Sheet'!D$17 -> 0.01071405 | G14: ='Data Sheet'!E25/'Data Sheet'!E$17 -> 0.017077846 | H14: ='Data Sheet'!F25/'Data Sheet'!F$17 -> -0.016933993 | I14: ='Data Sheet'!G25/'Data Sheet'!G$17 -> 0.0078201832 | J14: ='Data Sheet'!H25/'Data Sheet'!H$17 -> 0.0070822841 | K14: ='Data Sheet'!I25/'Data Sheet'!I$17 -> 0.023821098 | ... M14: ='Data Sheet'!K25/'Data Sheet'!K$17 -> 0.010678669
B15: ='Data Sheet'!A26 -> Depreciation | D15: ='Data Sheet'!B26/'Data Sheet'!B$17 -> 0.017598025 | E15: ='Data Sheet'!C26/'Data Sheet'!C$17 -> 0.018591204 | F15: ='Data Sheet'!D26/'Data Sheet'!D$17 -> 0.017026272 | G15: ='Data Sheet'!E26/'Data Sheet'!E$17 -> 0.01690271 | H15: ='Data Sheet'!F26/'Data Sheet'!F$17 -> 0.025080364 | I15: ='Data Sheet'!G26/'Data Sheet'!G$17 -> 0.021956502 | J15: ='Data Sheet'!H26/'Data Sheet'!H$17 -> 0.022374384 | K15: ='Data Sheet'!I26/'Data Sheet'!I$17 -> 0.022061704 | ... M15: ='Data Sheet'!K26/'Data Sheet'!K$17 -> 0.034097501
B16: ='Data Sheet'!A27 -> Interest | D16: ='Data Sheet'!B27/'Data Sheet'!B$17 -> 0.0176146 | E16: ='Data Sheet'!C27/'Data Sheet'!C$17 -> 0.013500896 | F16: ='Data Sheet'!D27/'Data Sheet'!D$17 -> 0.0062740725 | G16: ='Data Sheet'!E27/'Data Sheet'!E$17 -> 0.0072357443 | H16: ='Data Sheet'!F27/'Data Sheet'!F$17 -> 0.0080789257 | I16: ='Data Sheet'!G27/'Data Sheet'!G$17 -> 0.0059205156 | J16: ='Data Sheet'!H27/'Data Sheet'!H$17 -> 0.0058573708 | K16: ='Data Sheet'!I27/'Data Sheet'!I$17 -> 0.0063236587 | ... M16: ='Data Sheet'!K27/'Data Sheet'!K$17 -> 0.01647151
B17: ='Data Sheet'!A28 -> Profit before tax | D17: ='Data Sheet'!B28/'Data Sheet'!B$17 -> 0.025579594 | E17: ='Data Sheet'!C28/'Data Sheet'!C$17 -> 0.097640699 | F17: ='Data Sheet'!D28/'Data Sheet'!D$17 -> 0.11050496 | G17: ='Data Sheet'!E28/'Data Sheet'!E$17 -> 0.10131835 | H17: ='Data Sheet'!F28/'Data Sheet'!F$17 -> 0.083983058 | I17: ='Data Sheet'!G28/'Data Sheet'!G$17 -> 0.11300264 | J17: ='Data Sheet'!H28/'Data Sheet'!H$17 -> 0.1171788 | K17: ='Data Sheet'!I28/'Data Sheet'!I$17 -> 0.13012691 | ... M17: ='Data Sheet'!K28/'Data Sheet'!K$17 -> 0.10083549
B18: ='Data Sheet'!A29 -> Tax | D18: ='Data Sheet'!B29/'Data Sheet'!B$17 -> 0.030137692 | E18: ='Data Sheet'!C29/'Data Sheet'!C$17 -> 0.029251204 | F18: ='Data Sheet'!D29/'Data Sheet'!D$17 -> 0.02727226 | G18: ='Data Sheet'!E29/'Data Sheet'!E$17 -> 0.035976005 | H18: ='Data Sheet'!F29/'Data Sheet'!F$17 -> 0.02845056 | I18: ='Data Sheet'!G29/'Data Sheet'!G$17 -> 0.027346077 | J18: ='Data Sheet'!H29/'Data Sheet'!H$17 -> 0.030344368 | K18: ='Data Sheet'!I29/'Data Sheet'!I$17 -> 0.032433782 | ... M18: ='Data Sheet'!K29/'Data Sheet'!K$17 -> 0.022490252
B19: ='Data Sheet'!A30 -> Net profit | D19: ='Data Sheet'!B30/'Data Sheet'!B$17 -> -0.00083175872 | E19: ='Data Sheet'!C30/'Data Sheet'!C$17 -> 0.057443341 | F19: ='Data Sheet'!D30/'Data Sheet'!D$17 -> 0.072712333 | G19: ='Data Sheet'!E30/'Data Sheet'!E$17 -> 0.056290423 | H19: ='Data Sheet'!F30/'Data Sheet'!F$17 -> 0.047705714 | I19: ='Data Sheet'!G30/'Data Sheet'!G$17 -> 0.073839664 | J19: ='Data Sheet'!H30/'Data Sheet'!H$17 -> 0.075312043 | K19: ='Data Sheet'!I30/'Data Sheet'!I$17 -> 0.087336286 | ... M19: ='Data Sheet'!K30/'Data Sheet'!K$17 -> 0.07256489
B20: ='Data Sheet'!A31 -> Dividend Amount | D20: ='Data Sheet'!B31/'Data Sheet'!B$17 -> 0.021396692 | E20: ='Data Sheet'!C31/'Data Sheet'!C$17 -> 0.021876083 | F20: ='Data Sheet'!D31/'Data Sheet'!D$17 -> 0.021761171 | G20: ='Data Sheet'!E31/'Data Sheet'!E$17 -> 0.021758257 | H20: ='Data Sheet'!F31/'Data Sheet'!F$17 -> 0.025819151 | I20: ='Data Sheet'!G31/'Data Sheet'!G$17 -> 0.032171094 | J20: ='Data Sheet'!H31/'Data Sheet'!H$17 -> 0.044873513 | K20: ='Data Sheet'!I31/'Data Sheet'!I$17 -> 0.056953558 | ... M20: ='Data Sheet'!K31/'Data Sheet'!K$17 -> 0.046334777
B21: EBITDA | D21: ='Historical Financial'!C18/'Historical Financial'!C$6 -> 0.19733024 | E21: ='Historical Financial'!D18/'Historical Financial'!D$6 -> 0.25341652 | F21: ='Historical Financial'!E18/'Historical Financial'!E$6 -> 0.24893072 | G21: ='Historical Financial'!F18/'Historical Financial'!F$6 -> 0.2419003 | H21: ='Historical Financial'!G18/'Historical Financial'!G$6 -> 0.26670105 | I21: ='Historical Financial'!H18/'Historical Financial'!H$6 -> 0.25557769 | J21: ='Historical Financial'!I18/'Historical Financial'!I$6 -> 0.2744876 | K21: ='Historical Financial'!J18/'Historical Financial'!J$6 -> 0.2642159 | ... M21: ='Historical Financial'!L18/'Historical Financial'!L$6 -> 0.26862524
B23: ="Comman Size Balance Sheet" & "-" & 'Data Sheet'!B1 -> Comman Size Balance Sheet-TATA CONSUMER PRODUCTS LTD
B25: Particulars | D25: ='Historical Financial'!C$3 -> 42460 | E25: ='Historical Financial'!D$3 -> 42825 | F25: ='Historical Financial'!E$3 -> 43190 | G25: ='Historical Financial'!F$3 -> 43555 | H25: ='Historical Financial'!G$3 -> 43921 | I25: ='Historical Financial'!H$3 -> 44286 | J25: ='Historical Financial'!I$3 -> 44651 | K25: ='Historical Financial'!J$3 -> 45016 | ... M25: ='Historical Financial'!L$3 -> 45747
B27: Total Libilities | D27: ='Historical Financial'!C$53/'Historical Financial'!C$53 -> 1 | E27: ='Historical Financial'!D$53/'Historical Financial'!D$53 -> 1 | F27: ='Historical Financial'!E$53/'Historical Financial'!E$53 -> 1 | G27: ='Historical Financial'!F$53/'Historical Financial'!F$53 -> 1 | H27: ='Historical Financial'!G$53/'Historical Financial'!G$53 -> 1 | I27: ='Historical Financial'!H$53/'Historical Financial'!H$53 -> 1 | J27: ='Historical Financial'!I$53/'Historical Financial'!I$53 -> 1 | K27: ='Historical Financial'!J$53/'Historical Financial'!J$53 -> 1 | ... M27: ='Historical Financial'!L$53/'Historical Financial'!L$53 -> 1
B28: ='Historical Financial'!B49 -> Equity Share Capital | D28: ='Historical Financial'!C49/'Historical Financial'!C$53 -> 0.0063781234 | E28: ='Historical Financial'!D49/'Historical Financial'!D$53 -> 0.0066074014 | F28: ='Historical Financial'!E49/'Historical Financial'!E$53 -> 0.0060330225 | G28: ='Historical Financial'!F49/'Historical Financial'!F$53 -> 0.005800189 | H28: ='Historical Financial'!G49/'Historical Financial'!G$53 -> 0.0049888919 | I28: ='Historical Financial'!H49/'Historical Financial'!H$53 -> 0.004558355 | J28: ='Historical Financial'!I49/'Historical Financial'!I$53 -> 0.0043729807 | K28: ='Historical Financial'!J49/'Historical Financial'!J$53 -> 0.0040812758 | ... M28: ='Historical Financial'!L49/'Historical Financial'!L$53 -> 0.0031086419
B29: ='Historical Financial'!B50 -> Reserves | D29: ='Historical Financial'!C50/'Historical Financial'!C$53 -> 0.62498332 | E29: ='Historical Financial'!D50/'Historical Financial'!D$53 -> 0.64936905 | F29: ='Historical Financial'!E50/'Historical Financial'!E$53 -> 0.66615523 | G29: ='Historical Financial'!F50/'Historical Financial'!F$53 -> 0.66802626 | H29: ='Historical Financial'!G50/'Historical Financial'!G$53 -> 0.74285012 | I29: ='Historical Financial'!H50/'Historical Financial'!H$53 -> 0.71433765 | J29: ='Historical Financial'!I50/'Historical Financial'!I$53 -> 0.71411022 | K29: ='Historical Financial'!J50/'Historical Financial'!J$53 -> 0.71098592 | ... M29: ='Historical Financial'!L50/'Historical Financial'!L$53 -> 0.62525109
B30: ='Historical Financial'!B51 -> Borrowings | D30: ='Historical Financial'!C51/'Historical Financial'!C$53 -> 0.13684516 | E30: ='Historical Financial'!D51/'Historical Financial'!D$53 -> 0.082350145 | F30: ='Historical Financial'!E51/'Historical Financial'!E$53 -> 0.10205568 | G30: ='Historical Financial'!F51/'Historical Financial'!F$53 -> 0.10487396 | H30: ='Historical Financial'!G51/'Historical Financial'!G$53 -> 0.085872168 | I30: ='Historical Financial'!H51/'Historical Financial'!H$53 -> 0.080797534 | J30: ='Historical Financial'!I51/'Historical Financial'!I$53 -> 0.066999702 | K30: ='Historical Financial'!J51/'Historical Financial'!J$53 -> 0.070292837 | ... M30: ='Historical Financial'!L51/'Historical Financial'!L$53 -> 0.07516913
B31: ='Historical Financial'!B52 -> Other Liabilities | D31: ='Historical Financial'!C52/'Historical Financial'!C$53 -> 0.23179339 | E31: ='Historical Financial'!D52/'Historical Financial'!D$53 -> 0.26167341 | F31: ='Historical Financial'!E52/'Historical Financial'!E$53 -> 0.22575606 | G31: ='Historical Financial'!F52/'Historical Financial'!F$53 -> 0.22129959 | H31: ='Historical Financial'!G52/'Historical Financial'!G$53 -> 0.16628882 | I31: ='Historical Financial'!H52/'Historical Financial'!H$53 -> 0.20030646 | J31: ='Historical Financial'!I52/'Historical Financial'!I$53 -> 0.2145171 | K31: ='Historical Financial'!J52/'Historical Financial'!J$53 -> 0.21463996 | ... M31: ='Historical Financial'!L52/'Historical Financial'!L$53 -> 0.29647113
B33: Total Assets | D33: ='Historical Financial'!C$66/'Historical Financial'!C$66 -> 1 | E33: ='Historical Financial'!D$66/'Historical Financial'!D$66 -> 1 | F33: ='Historical Financial'!E$66/'Historical Financial'!E$66 -> 1 | G33: ='Historical Financial'!F$66/'Historical Financial'!F$66 -> 1 | H33: ='Historical Financial'!G$66/'Historical Financial'!G$66 -> 1 | I33: ='Historical Financial'!H$66/'Historical Financial'!H$66 -> 1 | J33: ='Historical Financial'!I$66/'Historical Financial'!I$66 -> 1 | K33: ='Historical Financial'!J$66/'Historical Financial'!J$66 -> 1 | ... M33: ='Historical Financial'!L$66/'Historical Financial'!L$66 -> 1
B34: ='Historical Financial'!B55 -> Net Block | D34: ='Historical Financial'!C55/'Historical Financial'!C$66 -> 0.47113826 | E34: ='Historical Financial'!D55/'Historical Financial'!D$66 -> 0.47873455 | F34: ='Historical Financial'!E55/'Historical Financial'!E$66 -> 0.45868369 | G34: ='Historical Financial'!F55/'Historical Financial'!F$66 -> 0.45156277 | H34: ='Historical Financial'!G55/'Historical Financial'!G$66 -> 0.63097574 | I34: ='Historical Financial'!H55/'Historical Financial'!H$66 -> 0.59467984 | J34: ='Historical Financial'!I55/'Historical Financial'!I$66 -> 0.59783761 | K34: ='Historical Financial'!J55/'Historical Financial'!J$66 -> 0.57419202 | ... M34: ='Historical Financial'!L55/'Historical Financial'!L$66 -> 0.67472264
B35: ='Historical Financial'!B56 -> Capital Work in Progress | D35: ='Historical Financial'!C56/'Historical Financial'!C$66 -> 0.0039839268 | E35: ='Historical Financial'!D56/'Historical Financial'!D$66 -> 0.0066157771 | F35: ='Historical Financial'!E56/'Historical Financial'!E$66 -> 0.012920667 | G35: ='Historical Financial'!F56/'Historical Financial'!F$66 -> 0.039005834 | H35: ='Historical Financial'!G56/'Historical Financial'!G$66 -> 0.005161576 | I35: ='Historical Financial'!H56/'Historical Financial'!H$66 -> 0.0055817096 | J35: ='Historical Financial'!I56/'Historical Financial'!I$66 -> 0.011718696 | K35: ='Historical Financial'!J56/'Historical Financial'!J$66 -> 0.012955525 | ... M35: ='Historical Financial'!L56/'Historical Financial'!L$66 -> 0.0068518929
B36: ='Historical Financial'!B57 -> Investments | D36: ='Historical Financial'!C57/'Historical Financial'!C$66 -> 0.1380468 | E36: ='Historical Financial'!D57/'Historical Financial'!D$66 -> 0.15191893 | F36: ='Historical Financial'!E57/'Historical Financial'!E$66 -> 0.11101775 | G36: ='Historical Financial'!F57/'Historical Financial'!F$66 -> 0.1091531 | H36: ='Historical Financial'!G57/'Historical Financial'!G$66 -> 0.071609762 | I36: ='Historical Financial'!H57/'Historical Financial'!H$66 -> 0.039860381 | J36: ='Historical Financial'!I57/'Historical Financial'!I$66 -> 0.037830838 | K36: ='Historical Financial'!J57/'Historical Financial'!J$66 -> 0.06295313 | ... M36: ='Historical Financial'!L57/'Historical Financial'!L$66 -> 0.030432018
B37: ='Historical Financial'!B58 -> Other Assets | D37: ='Historical Financial'!C58/'Historical Financial'!C$66 -> 0.11168841 | E37: ='Historical Financial'!D58/'Historical Financial'!D$66 -> 0.088401608 | F37: ='Historical Financial'!E58/'Historical Financial'!E$66 -> 0.098593219 | G37: ='Historical Financial'!F58/'Historical Financial'!F$66 -> 0.094902157 | H37: ='Historical Financial'!G58/'Historical Financial'!G$66 -> 0.061868539 | I37: ='Historical Financial'!H58/'Historical Financial'!H$66 -> 0.058888149 | J37: ='Historical Financial'!I58/'Historical Financial'!I$66 -> 0.082075002 | K37: ='Historical Financial'!J58/'Historical Financial'!J$66 -> 0.073262635 | ... M37: ='Historical Financial'!L58/'Historical Financial'!L$66 -> 0.059045347
B38: ='Historical Financial'!B61 -> Receivables | D38: ='Historical Financial'!C61/'Historical Financial'!C$66 -> 0.059873105 | E38: ='Historical Financial'!D61/'Historical Financial'!D$66 -> 0.062027491 | F38: ='Historical Financial'!E61/'Historical Financial'!E$66 -> 0.061972553 | G38: ='Historical Financial'!F61/'Historical Financial'!F$66 -> 0.062546642 | H38: ='Historical Financial'!G61/'Historical Financial'!G$66 -> 0.049932767 | I38: ='Historical Financial'!H61/'Historical Financial'!H$66 -> 0.03765589 | J38: ='Historical Financial'!I61/'Historical Financial'!I$66 -> 0.039627765 | K38: ='Historical Financial'!J61/'Historical Financial'!J$66 -> 0.035072174 | ... M38: ='Historical Financial'!L61/'Historical Financial'!L$66 -> 0.027325575
B39: ='Historical Financial'!B62 -> Inventory | D39: ='Historical Financial'!C62/'Historical Financial'!C$66 -> 0.1646336 | E39: ='Historical Financial'!D62/'Historical Financial'!D$66 -> 0.15211995 | F39: ='Historical Financial'!E62/'Historical Financial'!E$66 -> 0.1384517 | G39: ='Historical Financial'!F62/'Historical Financial'!F$66 -> 0.14783451 | H39: ='Historical Financial'!G62/'Historical Financial'!G$66 -> 0.09267722 | I39: ='Historical Financial'!H62/'Historical Financial'!H$66 -> 0.11124642 | J39: ='Historical Financial'!I62/'Historical Financial'!I$66 -> 0.10754562 | K39: ='Historical Financial'!J62/'Historical Financial'!J$66 -> 0.11868956 | ... M39: ='Historical Financial'!L62/'Historical Financial'!L$66 -> 0.11309582
B40: ='Historical Financial'!B63 -> Cash & Bank | D40: ='Historical Financial'!C63/'Historical Financial'!C$66 -> 0.050635892 | E40: ='Historical Financial'!D63/'Historical Financial'!D$66 -> 0.06018169 | F40: ='Historical Financial'!E63/'Historical Financial'!E$66 -> 0.11836043 | G40: ='Historical Financial'!F63/'Historical Financial'!F$66 -> 0.094994982 | H40: ='Historical Financial'!G63/'Historical Financial'!G$66 -> 0.0877744 | I40: ='Historical Financial'!H63/'Historical Financial'!H$66 -> 0.15208761 | J40: ='Historical Financial'!I63/'Historical Financial'!I$66 -> 0.12336446 | K40: ='Historical Financial'!J63/'Historical Financial'!J$66 -> 0.12287496 | ... M40: ='Historical Financial'!L63/'Historical Financial'!L$66 -> 0.088526708

Sheet Data Sheet
A1: COMPANY NAME | B1: TATA CONSUMER PRODUCTS LTD | E1: =IF(B2<>B3, "A NEW VERSION OF THE WORKSHEET IS AVAILABLE", "")
A2: LATEST VERSION | B2: 2.1 | E2: PLEASE DO NOT MAKE ANY CHANGES TO THIS SHEET
A3: CURRENT VERSION | B3: 2.1
A5: META
A6: Number of shares | B6: =IF(B9>0, B9/B8, 0) -> 98.946939
A7: Face Value | B7: 1
A8: Current Price | B8: 1102.5
A9: Market Capitalization | B9: 109089
A15: PROFIT & LOSS
A16: Report Date | B16: 42460 | C16: 42825 | D16: 43190 | E16: 43555 | F16: 43921 | G16: 44286 | H16: 44651 | I16: 45016 | J16: 45382 | K16: 45747
A17: Sales | B17: 6636.54 | C17: 6779.55 | D17: 6815.35 | E17: 7251.5 | F17: 9637.42 | G17: 11602.03 | H17: 12425.37 | I17: 13783.16 | J17: 15205.85 | K17: 17618.3
A18: Raw Material Cost | B18: 3601.49 | C18: 3165.65 | D18: 3746.11 | E18: 4022.05 | F18: 5402.9 | G18: 6367.79 | H18: 6323.22 | I18: 7107.06 | J18: 7364.06 | K18: 8986.68
A19: Change in Inventory | B19: -20.11 | C19: 0.69 | D19: 46.8 | E19: 14.41 | F19: -7.78 | G19: 149.54 | H19: 39.78 | I19: 273.88 | J19: 121.6 | K19: 362.49
A20: Power and Fuel | B20: 81.26 | C20: 83.19 | D20: 87.07 | E20: 89.28 | F20: 103.84 | G20: 97.36 | H20: 123.9 | I20: 149.43 | J20: 156.9 | K20: 156.21
A21: Other Mfr. Exp | B21: 190.32 | C21: 597.61 | D21: 194.69 | E21: 209.59 | F21: 238.47 | G21: 941.75 | H21: 1139.59 | I21: 1578.2 | J21: 1696.28 | K21: 1882.25
A22: Employee Cost | B22: 805.06 | C22: 834.95 | D22: 821.37 | E22: 806.3 | F22: 884.8 | G22: 970.23 | H22: 1048 | I22: 1120.36 | J22: 1258.59 | K22: 1430.1
A23: Selling and admin | B23: 922.88 | C23: 926.92 | D23: 857.64 | E23: 968.23 | F23: 1278.16 | G23: 1421.46 | H23: 1691.83 | I23: 1785.26 | J23: 1927.15 | K23: 2253.37
A24: Other Expenses | B24: 649.51 | C24: 380.79 | D24: 316.36 | E24: 384.55 | F24: 429.32 | G24: 409.22 | H24: 419.83 | I24: 460.26 | J24: 640.37 | K24: 792.83
A25: Other Income | B25: 37.54 | C25: 88.4 | D25: 73.02 | E25: 123.84 | F25: -163.2 | G25: 90.73 | H25: 88 | I25: 328.33 | J25: -81.42 | K25: 188.14
A26: Depreciation | B26: 116.79 | C26: 126.04 | D26: 116.04 | E26: 122.57 | F26: 241.71 | G26: 254.74 | H26: 278.01 | I26: 304.08 | J26: 377.15 | K26: 600.74
A27: Interest | B27: 116.9 | C27: 91.53 | D27: 42.76 | E27: 52.47 | F27: 77.86 | G27: 68.69 | H27: 72.78 | I27: 87.16 | J27: 129.81 | K27: 290.2
... A31: Dividend Amount | B31: 142 | C31: 148.31 | D31: 148.31 | E31: 157.78 | F31: 248.83 | G31: 373.25 | H31: 557.57 | I31: 785 | J31: 738.42 | K31: 816.34
A40: Quarters
A41: Report Date | B41: 45199 | C41: 45291 | D41: 45382 | E41: 45473 | F41: 45565 | G41: 45657 | H41: 45747 | I41: 45838 | J41: 45930 | K41: 46022
A42: Sales | B42: 3733.78 | C42: 3803.92 | D42: 3926.94 | E42: 4352.07 | F42: 4214.45 | G42: 4443.56 | H42: 4608.22 | I42: 4778.91 | J42: 4965.9 | K42: 5112
A43: Expenses | B43: 3196.69 | C43: 3231.54 | D43: 3297.34 | E43: 3684.69 | F43: 3588.16 | G43: 3878.83 | H43: 3987.27 | I43: 4171.97 | J43: 4294.12 | K43: 4391.33
A44: Other Income | B44: 75.28 | C44: -31.94 | D44: -177.35 | E44: 22.07 | F44: 18.8 | G44: 45.44 | H44: 101.83 | I44: 41.17 | J44: 38.01 | K44: 10.15
A45: Depreciation | B45: 93.93 | C45: 85.51 | D45: 115.76 | E45: 148 | F45: 149.33 | G45: 150.32 | H45: 153.09 | I45: 148.93 | J45: 153.28 | K45: 159.29
A46: Interest | B46: 27.56 | C46: 33.19 | D46: 42.83 | E46: 93.6 | F46: 98.69 | G46: 57.92 | H46: 39.99 | I46: 33.76 | J46: 33.23 | K46: 31.62
A47: Profit before tax | B47: 490.88 | C47: 421.74 | D47: 293.66 | E47: 447.85 | F47: 397.07 | G47: 401.93 | H47: 529.7 | I47: 465.42 | J47: 523.28 | K47: 539.91
A48: Tax | B48: 131.7 | C48: 106.21 | D48: 25.95 | E48: 133.7 | F48: 37.73 | G48: 102.18 | H48: 122.63 | I48: 118.98 | J48: 126.23 | K48: 137.12
A49: Net profit | B49: 338.24 | C49: 278.87 | D49: 216.63 | E49: 290.32 | F49: 364.42 | G49: 278.88 | H49: 344.85 | I49: 334.15 | J49: 404.46 | K49: 384.61
A50: Operating Profit | B50: 537.09 | C50: 572.38 | D50: 629.6 | E50: 667.38 | F50: 626.29 | G50: 564.73 | H50: 620.95 | I50: 606.94 | J50: 671.78 | K50: 720.67
A55: BALANCE SHEET
A56: Report Date | B56: 42460 | C56: 42825 | D56: 43190 | E56: 43555 | F56: 43921 | G56: 44286 | H56: 44651 | I56: 45016 | J56: 45382 | K56: 45747
A57: Equity Share Capital | B57: 63.11 | C57: 63.11 | D57: 63.11 | E57: 63.11 | F57: 92.16 | G57: 92.16 | H57: 92.16 | I57: 92.9 | J57: 95.28 | K57: 98.95
A58: Reserves | B58: 6184.06 | C58: 6202.39 | D58: 6968.49 | E58: 7268.58 | F58: 13722.7 | G58: 14442.35 | H58: 15049.78 | I58: 16183.81 | J58: 15961.51 | K58: 19902.13
A59: Borrowings | B59: 1354.05 | C59: 786.56 | D59: 1067.58 | E59: 1141.1 | F59: 1586.32 | G59: 1633.55 | H59: 1412.01 | I59: 1600.04 | J59: 3477.22 | K59: 2392.68
A60: Other Liabilities | B60: 2293.54 | C60: 2499.35 | D60: 2361.58 | E60: 2407.89 | F60: 3071.86 | G60: 4049.76 | H60: 4520.92 | I60: 4885.74 | J60: 8344.78 | K60: 9436.86
A61: Total | B61: 9894.76 | C61: 9551.41 | D61: 10460.76 | E61: 10880.68 | F61: 18473.04 | G61: 20217.82 | H61: 21074.87 | I61: 22762.49 | J61: 27878.79 | K61: 31830.62
A62: Net Block | B62: 4661.8 | C62: 4572.59 | D62: 4798.18 | E62: 4913.31 | F62: 11656.04 | G62: 12023.13 | H62: 12599.35 | I62: 13070.04 | J62: 19357.9 | K62: 21476.84
A63: Capital Work in Progress | B63: 39.42 | C63: 63.19 | D63: 135.16 | E63: 424.41 | F63: 95.35 | G63: 112.85 | H63: 246.97 | I63: 294.9 | J63: 189.6 | K63: 218.1
A64: Investments | B64: 1365.94 | C64: 1451.04 | D64: 1161.33 | E64: 1187.66 | F64: 1322.85 | G64: 805.89 | H64: 797.28 | I64: 1432.97 | J64: 870.55 | K64: 968.67
A65: Other Assets | B65: 3827.6 | C65: 3464.59 | D65: 4366.09 | E65: 4355.3 | F65: 5398.8 | G65: 7275.95 | H65: 7431.27 | I65: 7964.58 | J65: 7460.74 | K65: 9167.01
A66: Total | B66: 9894.76 | C66: 9551.41 | D66: 10460.76 | E66: 10880.68 | F66: 18473.04 | G66: 20217.82 | H66: 21074.87 | I66: 22762.49 | J66: 27878.79 | K66: 31830.62
A67: Receivables | B67: 592.43 | C67: 592.45 | D67: 648.28 | E67: 680.55 | F67: 922.41 | G67: 761.32 | H67: 835.15 | I67: 798.33 | J67: 896.75 | K67: 869.79
... A70: No. of Equity Shares | B70: 631129729 | C70: 631129729 | D70: 631129729 | E70: 631129729 | F70: 921551715 | G70: 921551715 | H70: 921551715 | I70: 929011650 | J70: 952834816 | K70: 989498558
A71: New Bonus Shares
A72: Face value | B72: 1 | C72: 1 | D72: 1 | E72: 1 | F72: 1 | G72: 1 | H72: 1 | I72: 1 | J72: 1 | K72: 1
A80: CASH FLOW:
A81: Report Date | B81: 42460 | C81: 42825 | D81: 43190 | E81: 43555 | F81: 43921 | G81: 44286 | H81: 44651 | I81: 45016 | J81: 45382 | K81: 45747
A82: Cash from Operating Activity | B82: 115.98 | C82: 741.2 | D82: 355.58 | E82: 209.87 | F82: 1082.23 | G82: 1656.37 | H82: 1515.81 | I82: 1461.29 | J82: 1936.68 | K82: 2056.65
A83: Cash from Investing Activity | B83: 144.62 | C83: 145.05 | D83: -31.1 | E83: 53.17 | F83: -622.04 | G83: -346.5 | H83: -1317.11 | I83: -833.61 | J83: -1910.77 | K83: -2303.48
A84: Cash from Financing Activity | B84: -281.8 | C84: -815.84 | D84: -30.39 | E84: -223.73 | F84: -308.33 | G84: -426.03 | H84: -994.77 | I84: -714.4 | J84: 255.55 | K84: 452.7
A85: Net Cash Flow | B85: -21.2 | C85: 70.41 | D85: 294.09 | E85: 39.31 | F85: 151.86 | G85: 883.84 | H85: -796.07 | I85: -86.72 | J85: 281.46 | K85: 205.87
A90: PRICE: | B90: 119.76 | C90: 148.7 | D90: 255.57 | E90: 201.45 | F90: 291.23 | G90: 631.06 | H90: 767.86 | I90: 700.15 | J90: 1082.74 | K90: 1001.9
A92: DERIVED:
A93: Adjusted Equity Shares in Cr | B93: 65.54 | C93: 65.54 | D93: 65.54 | E93: 65.54 | F93: 95.7 | G93: 95.7 | H93: 95.7 | I93: 96.47 | J93: 98.95 | K93: 98.95

Sheet Cashflow Data 
C2: 42430 | D2: 42795 | E2: 43160 | F2: 43525 | G2: 43891 | H2: 44256 | I2: 44621 | J2: 44986 | K2: 45352 | L2: 45717
B3: Cash from Operating Activity - | C3: 116 | D3: 741 | E3: 356 | F3: 210 | G3: 1082 | H3: 1656 | I3: 1516 | J3: 1461 | K3: 1937 | L3: 2057
B4: Profit from operations | C4: 650 | D4: 803 | E4: 794 | F4: 799 | G4: 1293 | H4: 1579 | I4: 1749 | J4: 1875 | K4: 2323 | L4: 2514
B5: Receivables | C5: -48 | D5: -60 | E5: -114 | F5: -133 | G5: -177 | H5: 186 | I5: -149 | J5: -36 | K5: -45 | L5: 36
B6: Inventory | C6: -70 | D6: 158 | E6: -13 | F6: -156 | G6: 81 | H6: -533 | I6: -1 | J6: -368 | K6: -3 | L6: -734
B7: Payables | C7: -153 | D7: 51 | E7: -12 | F7: -133 | G7: 14 | H7: 531 | I7: 152 | J7: 379 | K7: 60 | L7: 704
B8: Working capital changes | C8: -272 | D8: 148 | E8: -139 | F8: -422 | G8: -82 | H8: 183 | I8: 2 | J8: -25 | K8: 11 | L8: 5
B9: Direct taxes | C9: -234 | D9: -211 | E9: -299 | F9: -167 | G9: -128 | H9: -106 | I9: -235 | J9: -389 | K9: -398 | L9: -462
B10: Other operating items | C10: -28 | D10: 0 | E10: 0 | F10: 0 | G10: 0 | H10: 0 | I10: 0 | J10: 0 | K10: 0 | L10: 0
B11: Cash from Investing Activity - | C11: 145 | D11: 145 | E11: -31 | F11: 53 | G11: -622 | H11: -346 | I11: -1317 | J11: -834 | K11: -1911 | L11: -2303
B12: Fixed assets purchased | C12: -154 | D12: -138 | E12: -359 | F12: -282 | G12: -160 | H12: -211 | I12: -273 | J12: -312 | K12: -335 | L12: -460
B13: Fixed assets sold | C13: 8 | D13: 6 | E13: 9 | F13: 26 | G13: 9 | H13: 32 | I13: 27 | J13: 172 | K13: 24 | L13: 45
B14: Investments purchased | C14: 0 | D14: 0 | E14: -372 | F14: 0 | G14: -222 | H14: 0 | I14: 0 | J14: -533 | K14: 0 | L14: -29
... B35: Net Cash Flow | C35: -21 | D35: 70 | E35: 294 | F35: 39 | G35: 152 | H35: 884 | I35: -796 | J35: -87 | K35: 281 | L35: 206

Sheet Companies Data 
B3: S.No. | C3: Name | D3: CMP Rs. | E3: Mar Cap Rs.Cr. | F3: Debt Rs.Cr. | G3: Debt / Eq
B4: 1 | C4: Tata Consumer | D4: 1050.2 | E4: 103923.78 | F4: 2576.11 | G4: 0.13
B5: 2 | C5: Hind. Unilever | D5: 2082.7 | E5: 489349.37 | F5: 1775 | G5: 0.04
B6: 3 | C6: Nestle India | D6: 1291.7 | E6: 249080.36 | F6: 476.85 | G6: 0.1
B7: 4 | C7: Britannia Inds. | D7: 6002.5 | E7: 144581.19 | F7: 2196.3 | G7: 0.59
B8: 5 | C8: Dabur India | D8: 518.5 | E8: 91965.84 | F8: 1301.43 | G8: 0.12

Sheet DCF

Sheet Beta
B2: Beta
B4: Weekly Return on Tata consumer Products | F4: Nifty Return | I4: Beta Drifting
B6: Date | C6: Close Price | D6: Return | F6: Close Price | G6: Return | I6: Levered Beta | K6: =N8 -> 0.90141259 | M6: Beta 1 | N6: =SLOPE(D7:D111,G7:G111) -> 0.90141259
B7: 45369 | C7: 1106.8589 | D7: - | F7: 22096.75 | G7: - | I7: Raw Beta weight | K7: 0.75 | M7: Beta 2 | N7: =_xlfn.COVARIANCE.S(D7:D111,G7:G111)/_xlfn.VAR.S(G7:G111) -> 0.90141259
B8: 45376 | C8: 1080.6847 | D8: =C8/C7-1 -> -0.023647273 | F8: 22326.9 | G8: =F8/F7-1 -> 0.010415577 | M8: Beta 3 | N8: =J32 -> 0.90141259
B9: 45383 | C9: 1099.7609 | D9: =C9/C8-1 -> 0.017651931 | F9: 22513.699 | G9: =F9/F8-1 -> 0.0083665365 | I9: Market Beta | K9: 1
B10: 45390 | C10: 1133.181 | D10: =C10/C9-1 -> 0.030388575 | F10: 22519.4 | G10: =F10/F9-1 -> 0.00025323124 | I10: Market Beta weight | K10: 0.25
B11: 45397 | C11: 1121.9916 | D11: =C11/C10-1 -> -0.0098743738 | F11: 22147 | G11: =F11/F10-1 -> -0.01653687
B12: 45404 | C12: 1087.0435 | D12: =C12/C11-1 -> -0.031148291 | F12: 22419.949 | G12: =F12/F11-1 -> 0.012324433 | I12: Adjusted Beta | K12: =(K6*K7)+(K9*K10) -> 0.92605944
B13: 45411 | C13: 1078.8116 | D13: =C13/C12-1 -> -0.0075726609 | F13: 22475.85 | G13: =F13/F12-1 -> 0.0024933326
B14: 45418 | C14: 1075.5089 | D14: =C14/C13-1 -> -0.003061456 | F14: 22055.199 | G14: =F14/F13-1 -> -0.018715661
B15: 45425 | C15: 1079.6989 | D15: =C15/C14-1 -> 0.0038957756 | F15: 22466.1 | G15: =F15/F14-1 -> 0.018630545 | I15: SUMMARY OUTPUT
B16: 45432 | C16: 1082.7057 | D16: =C16/C15-1 -> 0.0027848839 | F16: 22957.1 | G16: =F16/F15-1 -> 0.021855151
B17: 45439 | C17: 1052.4498 | D17: =C17/C16-1 -> -0.027944676 | F17: 22530.699 | G17: =F17/F16-1 -> -0.018573792 | I17: Regression Statistics
B18: 45446 | C18: 1127.2952 | D18: =C18/C17-1 -> 0.071115349 | F18: 23290.15 | G18: =F18/F17-1 -> 0.033707395 | I18: Multiple R | J18: 0.5286841
B19: 45453 | C19: 1104.2657 | D19: =C19/C18-1 -> -0.020428917 | F19: 23465.6 | G19: =F19/F18-1 -> 0.0075331939 | I19: R Square | J19: 0.27950687
B20: 45460 | C20: 1076.9186 | D20: =C20/C19-1 -> -0.024765024 | F20: 23501.1 | G20: =F20/F19-1 -> 0.0015128529 | I20: Adjusted R Square | J20: 0.27244321
B21: 45467 | C21: 1089.3761 | D21: =C21/C20-1 -> 0.011567745 | F21: 24010.6 | G21: =F21/F20-1 -> 0.021679837 | I21: Standard Error | J21: 0.026194776
B22: 45474 | C22: 1129.0323 | D22: =C22/C21-1 -> 0.036402717 | F22: 24323.85 | G22: =F22/F21-1 -> 0.013046321 | I22: Observations | J22: 104
B23: 45481 | C23: 1143.7731 | D23: =C23/C22-1 -> 0.013056068 | F23: 24502.15 | G23: =F23/F22-1 -> 0.0073302863
B24: 45488 | C24: 1164.7821 | D24: =C24/C23-1 -> 0.018368183 | F24: 24530.9 | G24: =F24/F23-1 -> 0.0011733664 | I24: ANOVA
B25: 45495 | C25: 1204.7213 | D25: =C25/C24-1 -> 0.034288996 | F25: 24834.85 | G25: =F25/F24-1 -> 0.012390463 | J25: df | K25: SS | L25: MS | M25: F | N25: Significance F
B26: 45502 | C26: 1184.8685 | D26: =C26/C25-1 -> -0.01647915 | F26: 24717.699 | G26: =F26/F25-1 -> -0.0047171774 | I26: Regression | J26: 1 | K26: 0.027151398 | L26: 0.027151398 | M26: 39.569706 | N26: 7.9858833e-09
B27: 45509 | C27: 1177.4237 | D27: =C27/C26-1 -> -0.0062832492 | F27: 24367.5 | G27: =F27/F26-1 -> -0.014167954 | I27: Residual | J27: 102 | K27: 0.069988961 | L27: 0.00068616628
B28: 45516 | C28: 1179.0118 | D28: =C28/C27-1 -> 0.0013488218 | F28: 24541.15 | G28: =F28/F27-1 -> 0.0071263113 | I28: Total | J28: 103 | K28: 0.097140359
B29: 45523 | C29: 1187.9954 | D29: =C29/C28-1 -> 0.0076195337 | F29: 24823.15 | G29: =F29/F28-1 -> 0.011490904
B30: 45530 | C30: 1191.3207 | D30: =C30/C29-1 -> 0.0027990996 | F30: 25235.9 | G30: =F30/F29-1 -> 0.016627624 | J30: Coefficients | K30: Standard Error | L30: t Stat | M30: P-value | N30: Lower 95% | O30: Upper 95% | P30: Lower 95.0% | Q30: Upper 95.0%
B31: 45537 | C31: 1165.2141 | D31: =C31/C30-1 -> -0.021913971 | F31: 24852.15 | G31: =F31/F30-1 -> -0.015206511 | I31: Intercept | J31: -0.00057206303 | K31: 0.0025700205 | L31: -0.22259084 | M31: 0.82429908 | N31: -0.0056696865 | O31: 0.0045255604 | P31: -0.0056696865 | Q31: 0.0045255604
B32: 45544 | C32: 1201.396 | D32: =C32/C31-1 -> 0.031051705 | F32: 25356.5 | G32: =F32/F31-1 -> 0.020294003 | I32: X Variable 1 | J32: 0.90141259 | K32: 0.14329869 | L32: 6.2904456 | M32: 7.9858833e-09 | N32: 0.61718032 | O32: 1.1856449 | P32: 0.61718032 | Q32: 1.1856449
B33: 45551 | C33: 1207.8977 | D33: =C33/C32-1 -> 0.0054117951 | F33: 25790.949 | G33: =F33/F32-1 -> 0.017133643
B34: 45558 | C34: 1192.7103 | D34: =C34/C33-1 -> -0.012573397 | F34: 26178.949 | G34: =F34/F33-1 -> 0.015044037
B35: 45565 | C35: 1122.0839 | D35: =C35/C34-1 -> -0.059215103 | F35: 25014.6 | G35: =F35/F34-1 -> -0.04447656
B36: 45572 | C36: 1104.911 | D36: =C36/C35-1 -> -0.015304428 | F36: 24964.25 | G36: =F36/F35-1 -> -0.0020128089
B37: 45579 | C37: 1085.207 | D37: =C37/C36-1 -> -0.017833092 | F37: 24854.051 | G37: =F37/F36-1 -> -0.0044142812
B38: 45586 | C38: 965.89136 | D38: =C38/C37-1 -> -0.10994738 | F38: 24180.801 | G38: =F38/F37-1 -> -0.02708814
B39: 45593 | C39: 996.71295 | D39: =C39/C38-1 -> 0.031910001 | F39: 24304.35 | G39: =F39/F38-1 -> 0.005109377
B40: 45600 | C40: 985.64502 | D40: =C40/C39-1 -> -0.011104433 | F40: 24148.199 | G40: =F40/F39-1 -> -0.006424792
B41: 45607 | C41: 918.19489 | D41: =C41/C40-1 -> -0.068432481 | F41: 23532.699 | G41: =F41/F40-1 -> -0.025488443
B42: 45614 | C42: 938.24628 | D42: =C42/C41-1 -> 0.021837838 | F42: 23907.25 | G42: =F42/F41-1 -> 0.015916184
B43: 45621 | C43: 951.59735 | D43: =C43/C42-1 -> 0.014229818 | F43: 24131.1 | G43: =F43/F42-1 -> 0.0093632521
B44: 45628 | C44: 967.28113 | D44: =C44/C43-1 -> 0.016481526 | F44: 24677.801 | G44: =F44/F43-1 -> 0.02265546
... B111: 46097 | C111: 1050.2 | D111: =C111/C110-1 -> -0.030823205 | F111: 23114.5 | G111: =F111/F110-1 -> -0.0015809016

Sheet Market Return
B2: Return on Market :-
B4: Year | C4: Annual
B5: 2000 | C5: -0.1465
B6: 2001 | C6: -0.1618 | E6: Avgrage Return | G6: =AVERAGE(C5:C30) -> 0.15149231
B7: 2002 | C7: 0.0325 | E7: Dividend Yied | G7: 1.28% 1
B8: 2003 | C8: 0.719
B9: 2004 | C9: 0.1068 | E9: Total Market return | G9: =SUM(G6:G7) -> 0.15149231
B10: 2005 | C10: 0.3634
B11: 2006 | C11: 0.3983
B12: 2007 | C12: 0.5477
B13: 2008 | C13: -0.5179
B14: 2009 | C14: 0.7576
B15: 2010 | C15: 0.1795
B16: 2011 | C16: -0.2462
B17: 2012 | C17: 0.277
B18: 2013 | C18: 0.0676
B19: 2014 | C19: 0.3139
B20: 2015 | C20: -0.0406
B21: 2016 | C21: 0.0301
... B30: 2025 | C30: 0.1051

Sheet WACC
B2: Weighted Average Cost Of Capital
B4: Peer Comps
H5: Debt/ | I5: Debt/ | J5: Levered | K5: Unlevered
B6: Name Of the Company | D6: Country | E6: Total Debt | F6: Total Equity | G6: Tax Rate 1 | H6: Equity | I6: Capital | J6: Beta 2 | K6: Beta 3
B8: Tata consumer Product | D8: India | E8: ='Companies Data '!F4 -> 2576.11 | F8: ='Companies Data '!E4 -> 103923.78 | G8: 0.3 | H8: ='Companies Data '!G4 -> 0.13 | I8: =E8/(E8+F8) -> 0.024188851 | J8: =Beta!N8 -> 0.90141259 | K8: =J8/(1+(1-G8)*H8) -> 0.82622602
B9: Hind. Unilever | D9: India | E9: ='Companies Data '!F5 -> 1775 | F9: ='Companies Data '!E5 -> 489349.37 | G9: 0.3 | H9: ='Companies Data '!G5 -> 0.04 | I9: =E9/(E9+F9) -> 0.0036141558 | J9: 1.0538753 | K9: =J9/(1+(1-G9)*H9) -> 1.0251705
B10: Nestle India | D10: India | E10: ='Companies Data '!F6 -> 476.85 | F10: ='Companies Data '!E6 -> 249080.36 | G10: 0.3 | H10: ='Companies Data '!G6 -> 0.1 | I10: =E10/(E10+F10) -> 0.0019107843 | J10: 0.76940736 | K10: =J10/(1+(1-G10)*H10) -> 0.7190723
B11: Britannia Industries | D11: India | E11: ='Companies Data '!F7 -> 2196.3 | F11: ='Companies Data '!E7 -> 144581.19 | G11: 0.3 | H11: ='Companies Data '!G7 -> 0.59 | I11: =E11/(E11+F11) -> 0.014963466 | J11: 0.51902358 | K11: =J11/(1+(1-G11)*H11) -> 0.3673203
B12: Dabur India | D12: India | E12: ='Companies Data '!D8 -> 518.5 | F12: ='Companies Data '!E8 -> 91965.84 | G12: 0.3 | H12: ='Companies Data '!G8 -> 0.12 | I12: =E12/(E12+F12) -> 0.0056063545 | J12: 0.86261383 | K12: =J12/(1+(1-G12)*H12) -> 0.79576922
F14: Average | G14: =AVERAGE(G8:G12) -> 0.3 | H14: =AVERAGE(H8:H12) -> 0.196 | I14: =AVERAGE(I8:I12) -> 0.010056722 | J14: =AVERAGE(J8:J12) -> 0.82126653 | K14: =AVERAGE(K8:K12) -> 0.74671167
F15: Median | G15: =MEDIAN(G8:G12) -> 0.3 | H15: =MEDIAN(H8:H12) -> 0.12 | I15: =MEDIAN(I8:I12) -> 0.0056063545 | J15: =MEDIAN(J8:J12) -> 0.86261383 | K15: =MEDIAN(K8:K12) -> 0.79576922
B17: Cost of Debt | H17: Cost of Equity
B19: Pre-Tax cost of Debt | E19: ='Data Sheet'!K27/'Companies Data '!F4 -> 0.11265047 | H19: Risk Free Rate | K19: 0.0676
B20: Tax Rate | E20: =G14 -> 0.3 | H20: Equity Risk Premium | K20: ='Market Return'!G9-WACC!K19 -> 0.083892308
B21: Post-Tax cost of Debt | E21: =E19*(1-E20) -> 0.078855328 | H21: Levered Beta 4 | K21: =K29 -> 0.79020639
H22: Cost Of Equity | K22: =K19+(K20*K21) -> 0.13389224
B24: Capital Structure | H24: Levered Beta
D26: Current | E26: Target | H26: Comps Median Unlevered Beta | K26: =K15 -> 0.79576922
B27: Total Debt | C27: =E8 -> 2576.11 | D27: =C27/C29 -> 0.024188851 | E27: =I14 -> 0.010056722 | H27: Target Debt/Equity | K27: =E27 -> 0.010056722
B28: Market Capitalization | C28: =F8 -> 103923.78 | D28: =C28/C29 -> 0.97581115 | E28: =E29-E27 -> 0.98994328 | H28: Tax Rate | K28: =G15 -> 0.3
B29: Total Capital | C29: =SUM(C27:C28) -> 106499.89 | D29: =SUM(D27:D28) -> 1 | E29: 1 | H29: Levered Beta | K29: =K26/(1+(1-K28)*K27) -> 0.79020639
B31: Notes: | H31: Weighted Average Cost Of Capital
B32: 1. Tax Rate considered as Marginal Tax Rate for the country
B33: 2. Levered Beta is based on 5 Year Monthly data | H33: Cost of Equity | K33: =K22 -> 0.13389224
B34: 3.UnLevered beta = Levered Beta/(1+(1-Tax Rate)* Debt/Equity) | H34: Equity Weight | K34: =E28 -> 0.98994328
B35: 4.Levered beta = UnLevered Beta*(1+(1-Tax Rate)* Debt/Equity)
H36: Cost of Debt | K36: =E21 -> 0.078855328
H37: Debt Weight | K37: =E27 -> 0.010056722
H39: WACC | K39: =(K33*K34)+(K36*K37) -> 0.13333875

Sheet Raw Financial 
B2: Balance sheet
B3: Particular | D3: ='Data Sheet'!B16 -> 42460 | E3: ='Data Sheet'!C16 -> 42825 | F3: ='Data Sheet'!D16 -> 43190 | G3: ='Data Sheet'!E16 -> 43555 | H3: ='Data Sheet'!F16 -> 43921 | I3: ='Data Sheet'!G16 -> 44286 | J3: ='Data Sheet'!H16 -> 44651 | K3: ='Data Sheet'!I16 -> 45016 | ... M3: ='Data Sheet'!K16 -> 45747
B5: Equity Capital | D5: 63 | E5: 63 | F5: 63 | G5: 63 | H5: 92 | I5: 92 | J5: 92 | K5: 93 | L5: 95 | M5: 99
B6: Reserves | D6: 6184 | E6: 6202 | F6: 6968 | G6: 7269 | H6: 13723 | I6: 14442 | J6: 15050 | K6: 16184 | L6: 15962 | M6: 19902
B7: Borrowings -
B8: Long term Borrowings | D8: 504 | E8: 450 | F8: 656 | G8: 787 | H8: 795 | I8: 288 | J8: 242 | K8: 206 | L8: 168 | M8: 191
B9: Short term Borrowings | D9: 409 | E9: 320 | F9: 400 | G9: 330 | H9: 388 | I9: 919 | J9: 769 | K9: 977 | L9: 2786 | M9: 1658
B10: Lease Liabilities | D10: 0 | E10: 0 | F10: 0 | G10: 0 | H10: 330 | I10: 427 | J10: 401 | K10: 417 | L10: 523 | M10: 544
B11: Other Borrowings | D11: 441 | E11: 16 | F11: 11 | G11: 24 | H11: 74 | I11: 0 | J11: 0 | K11: 0 | L11: 0 | M11: 0
B12: Other Liabilities -
B13: Non controlling int | D13: 862 | E13: 920 | F13: 1009 | G13: 1028 | H13: 1092 | I13: 1093 | J13: 1152 | K13: 850 | L13: 1379 | M13: 1389
B14: Trade Payables | D14: 677 | E14: 738 | F14: 706 | G14: 665 | H14: 944 | I14: 1625 | J14: 1916 | K14: 2348 | L14: 2707 | M14: 3508
B15: Advance from Customers | D15: 3 | E15: 6 | F15: 9 | G15: 6 | H15: 13 | I15: 41 | J15: 44 | K15: 52 | L15: 64 | M15: 65
B16: Other liability items | D16: 751 | E16: 836 | F16: 638 | G16: 710 | H16: 1022 | I16: 1291 | J16: 1409 | K16: 1636 | L16: 4195 | M16: 4474
B17: Total Liabilities | D17: 9895 | E17: 9551 | F17: 10461 | G17: 10881 | H17: 18473 | I17: 20218 | J17: 21075 | K17: 22762 | L17: 27879 | M17: 31831
B19: Fixed Assets -
B20: Land | D20: 68 | E20: 60 | F20: 59 | G20: 63 | H20: 150 | I20: 146 | J20: 168 | K20: 172 | L20: 204 | M20: 192
B21: Building | D21: 266 | E21: 229 | F21: 254 | G21: 316 | H21: 528 | I21: 640 | J21: 714 | K21: 728 | L21: 963 | M21: 1027
B22: Estates | D22: 0 | E22: 0 | F22: 0 | G22: 0 | H22: 0 | I22: 0 | J22: 0 | K22: 0 | L22: 0 | M22: 0
B23: Plant Machinery | D23: 1387 | E23: 1305 | F23: 1409 | G23: 1465 | H23: 1956 | I23: 2054 | J23: 2273 | K23: 2442 | L23: 2811 | M23: 2785
B24: Equipments | D24: 9 | E24: 5 | F24: 7 | G24: 7 | H24: 8 | I24: 10 | J24: 9 | K24: 7 | L24: 0 | M24: 0
B25: Furniture n fittings | D25: 171 | E25: 165 | F25: 178 | G25: 190 | H25: 217 | I25: 229 | J25: 229 | K25: 246 | L25: 264 | M25: 295
B26: Vehicles | D26: 23 | E26: 24 | F26: 23 | G26: 22 | H26: 27 | I26: 25 | J26: 23 | K26: 20 | L26: 27 | M26: 34
B27: Intangible Assets | D27: 4408 | E27: 4173 | F27: 4408 | G27: 4485 | H27: 10566 | I27: 10812 | J27: 11008 | K27: 11405 | L27: 17596 | M27: 19944
B28: Other fixed assets | D28: 149 | E28: 327 | F28: 331 | G28: 349 | H28: 668 | I28: 576 | J28: 802 | K28: 881 | L28: 646 | M28: 720
B30: Gross Block | D30: 6480 | E30: 6287 | F30: 6669 | G30: 6898 | H30: 14120 | I30: 14492 | J30: 15226 | K30: 15900 | L30: 22510 | M30: 24997
B31: Accumulated Depreciation | D31: 1818 | E31: 1715 | F31: 1870 | G31: 1984 | H31: 2464 | I31: 2469 | J31: 2627 | K31: 2830 | L31: 3152 | M31: 3520
B32: Net Block | D32: =D30-D31 -> 4662 | E32: =E30-E31 -> 4572 | F32: =F30-F31 -> 4799 | G32: =G30-G31 -> 4914 | H32: =H30-H31 -> 11656 | I32: =I30-I31 -> 12023 | J32: =J30-J31 -> 12599 | K32: =K30-K31 -> 13070 | ... M32: =M30-M31 -> 21477
B34: CWIP | D34: 39 | E34: 63 | F34: 135 | G34: 424 | H34: 95 | I34: 113 | J34: 247 | K34: 295 | L34: 190 | M34: 218
B35: Investments | D35: 1366 | E35: 1451 | F35: 1161 | G35: 1188 | H35: 1323 | I35: 806 | J35: 797 | K35: 1433 | L35: 871 | M35: 969
B37: Other Assets -
B38: Inventories | D38: 1629 | E38: 1453 | F38: 1448 | G38: 1609 | H38: 1712 | I38: 2249 | J38: 2267 | K38: 2702 | L38: 2769 | M38: 3600
B39: Trade receivables - | D39: 592 | E39: 592 | F39: 648 | G39: 681 | H39: 922 | I39: 761 | J39: 835 | K39: 798 | L39: 897 | M39: 870
B40: Prov for Doubtful | D40: -6 | E40: -7 | F40: -13 | G40: -7 | H40: -15 | I40: -38 | J40: -39 | K40: -40 | L40: -41 | M40: -64
B41: Cash Equivalents | D41: 501 | E41: 575 | F41: 1238 | G41: 1034 | H41: 1621 | I41: 3075 | J41: 2600 | K41: 2797 | L41: 2454 | M41: 2818
B42: Loans n Advances | D42: 241 | E42: 428 | F42: 333 | G42: 108 | H42: 133 | I42: 207 | J42: 235 | K42: 235 | L42: 591 | M42: 737
B43: Other asset items | D43: 864 | E43: 417 | F43: 698 | G43: 925 | H43: 1010 | I43: 983 | J43: 1495 | K43: 1433 | L43: 749 | M43: 1143
B44: Total Assets | D44: 9895 | E44: 9551 | F44: 10461 | G44: 10881 | H44: 18473 | I44: 20218 | J44: 21075 | K44: 22762 | L44: 27879 | M44: 31831

Sheet Internsic Growth
B2: Calculation Of ROIC | E2: ='Raw Financial '!H3 -> 43921 | F2: ='Raw Financial '!I3 -> 44286 | G2: ='Raw Financial '!J3 -> 44651 | H2: ='Raw Financial '!K3 -> 45016 | I2: ='Raw Financial '!L3 -> 45382 | J2: ='Raw Financial '!M3 -> 45747
B4: Current Assests
B6: ='Raw Financial '!B38 -> Inventories | E6: ='Raw Financial '!H38 -> 1712 | F6: ='Raw Financial '!I38 -> 2249 | G6: ='Raw Financial '!J38 -> 2267 | H6: ='Raw Financial '!K38 -> 2702 | I6: ='Raw Financial '!L38 -> 2769 | J6: ='Raw Financial '!M38 -> 3600
B7: ='Raw Financial '!B39 -> Trade receivables - | E7: ='Raw Financial '!H39 -> 922 | F7: ='Raw Financial '!I39 -> 761 | G7: ='Raw Financial '!J39 -> 835 | H7: ='Raw Financial '!K39 -> 798 | I7: ='Raw Financial '!L39 -> 897 | J7: ='Raw Financial '!M39 -> 870
B8: ='Raw Financial '!B42 -> Loans n Advances | E8: ='Raw Financial '!D42 -> 241 | F8: ='Raw Financial '!E42 -> 428 | G8: ='Raw Financial '!F42 -> 333 | H8: ='Raw Financial '!G42 -> 108 | I8: ='Raw Financial '!H42 -> 133 | J8: ='Raw Financial '!I42 -> 207
B9: ='Raw Financial '!B43 -> Other asset items | E9: ='Raw Financial '!H43 -> 1010 | F9: ='Raw Financial '!I43 -> 983 | G9: ='Raw Financial '!J43 -> 1495 | H9: ='Raw Financial '!K43 -> 1433 | I9: ='Raw Financial '!L43 -> 749 | J9: ='Raw Financial '!M43 -> 1143
B10: Total Current Assets | E10: =SUM(E6:E9) -> 3885 | F10: =SUM(F6:F9) -> 4421 | G10: =SUM(G6:G9) -> 4930 | H10: =SUM(H6:H9) -> 5041 | I10: =SUM(I6:I9) -> 4548 | J10: =SUM(J6:J9) -> 5820
B12: Current Libilities
B14: ='Raw Financial '!B14 -> Trade Payables | E14: ='Raw Financial '!H14 -> 944 | F14: ='Raw Financial '!I14 -> 1625 | G14: ='Raw Financial '!J14 -> 1916 | H14: ='Raw Financial '!K14 -> 2348 | I14: ='Raw Financial '!L14 -> 2707 | J14: ='Raw Financial '!M14 -> 3508
B15: ='Raw Financial '!B15 -> Advance from Customers | E15: ='Raw Financial '!H15 -> 13 | F15: ='Raw Financial '!I15 -> 41 | G15: ='Raw Financial '!J15 -> 44 | H15: ='Raw Financial '!K15 -> 52 | I15: ='Raw Financial '!L15 -> 64 | J15: ='Raw Financial '!M15 -> 65
B16: ='Raw Financial '!B16 -> Other liability items | E16: ='Raw Financial '!H16 -> 1022 | F16: ='Raw Financial '!I16 -> 1291 | G16: ='Raw Financial '!J16 -> 1409 | H16: ='Raw Financial '!K16 -> 1636 | I16: ='Raw Financial '!L16 -> 4195 | J16: ='Raw Financial '!M16 -> 4474
B17: Total Current Libilities | E17: =SUM(E14:E16) -> 1979 | F17: =SUM(F14:F16) -> 2957 | G17: =SUM(G14:G16) -> 3369 | H17: =SUM(H14:H16) -> 4036 | I17: =SUM(I14:I16) -> 6966 | J17: =SUM(J14:J16) -> 8047
B19: Net Working Capital | E19: =E10-E17 -> 1906 | F19: =F10-F17 -> 1464 | G19: =G10-G17 -> 1561 | H19: =H10-H17 -> 1005 | I19: =I10-I17 -> -2418 | J19: =J10-J17 -> -2227
B21: Non Current Assets
B22: ='Raw Financial '!B20 -> Land | E22: ='Raw Financial '!H20 -> 150 | F22: ='Raw Financial '!I20 -> 146 | G22: ='Raw Financial '!J20 -> 168 | H22: ='Raw Financial '!K20 -> 172 | I22: ='Raw Financial '!L20 -> 204 | J22: ='Raw Financial '!M20 -> 192
B23: ='Raw Financial '!B21 -> Building | E23: ='Raw Financial '!H21 -> 528 | F23: ='Raw Financial '!I21 -> 640 | G23: ='Raw Financial '!J21 -> 714 | H23: ='Raw Financial '!K21 -> 728 | I23: ='Raw Financial '!L21 -> 963 | J23: ='Raw Financial '!M21 -> 1027
B24: ='Raw Financial '!B22 -> Estates | E24: ='Raw Financial '!H22 -> 0 | F24: ='Raw Financial '!I22 -> 0 | G24: ='Raw Financial '!J22 -> 0 | H24: ='Raw Financial '!K22 -> 0 | I24: ='Raw Financial '!L22 -> 0 | J24: ='Raw Financial '!M22 -> 0
B25: ='Raw Financial '!B23 -> Plant Machinery | E25: ='Raw Financial '!H23 -> 1956 | F25: ='Raw Financial '!I23 -> 2054 | G25: ='Raw Financial '!J23 -> 2273 | H25: ='Raw Financial '!K23 -> 2442 | I25: ='Raw Financial '!L23 -> 2811 | J25: ='Raw Financial '!M23 -> 2785
B26: ='Raw Financial '!B24 -> Equipments | E26: ='Raw Financial '!H24 -> 8 | F26: ='Raw Financial '!I24 -> 10 | G26: ='Raw Financial '!J24 -> 9 | H26: ='Raw Financial '!K24 -> 7 | I26: ='Raw Financial '!L24 -> 0 | J26: ='Raw Financial '!M24 -> 0
B27: ='Raw Financial '!B25 -> Furniture n fittings | E27: ='Raw Financial '!H25 -> 217 | F27: ='Raw Financial '!I25 -> 229 | G27: ='Raw Financial '!J25 -> 229 | H27: ='Raw Financial '!K25 -> 246 | I27: ='Raw Financial '!L25 -> 264 | J27: ='Raw Financial '!M25 -> 295
B28: ='Raw Financial '!B26 -> Vehicles | E28: ='Raw Financial '!H26 -> 27 | F28: ='Raw Financial '!I26 -> 25 | G28: ='Raw Financial '!J26 -> 23 | H28: ='Raw Financial '!K26 -> 20 | I28: ='Raw Financial '!L26 -> 27 | J28: ='Raw Financial '!M26 -> 34
B29: ='Raw Financial '!B27 -> Intangible Assets | E29: ='Raw Financial '!H27 -> 10566 | F29: ='Raw Financial '!I27 -> 10812 | G29: ='Raw Financial '!J27 -> 11008 | H29: ='Raw Financial '!K27 -> 11405 | I29: ='Raw Financial '!L27 -> 17596 | J29: ='Raw Financial '!M27 -> 19944
B30: ='Raw Financial '!B28 -> Other fixed assets | E30: ='Raw Financial '!H28 -> 668 | F30: ='Raw Financial '!I28 -> 576 | G30: ='Raw Financial '!J28 -> 802 | H30: ='Raw Financial '!K28 -> 881 | I30: ='Raw Financial '!L28 -> 646 | J30: ='Raw Financial '!M28 -> 720
E31: ='Raw Financial '!H29 -> 0 | F31: ='Raw Financial '!I29 -> 0 | G31: ='Raw Financial '!J29 -> 0 | H31: ='Raw Financial '!K29 -> 0 | I31: ='Raw Financial '!L29 -> 0 | J31: ='Raw Financial '!M29 -> 0
B32: ='Raw Financial '!B30 -> Gross Block | E32: =SUM(E22:E30) -> 14120 | F32: =SUM(F22:F30) -> 14492 | G32: =SUM(G22:G30) -> 15226 | H32: =SUM(H22:H30) -> 15901 | I32: =SUM(I22:I30) -> 22511 | J32: =SUM(J22:J30) -> 24997
B33: ='Raw Financial '!B31 -> Accumulated Depreciation | E33: =-'Raw Financial '!H31 -> -2464 | F33: =-'Raw Financial '!I31 -> -2469 | G33: =-'Raw Financial '!J31 -> -2627 | H33: =-'Raw Financial '!K31 -> -2830 | I33: =-'Raw Financial '!L31 -> -3152 | J33: =-'Raw Financial '!M31 -> -3520
B35: Net Non- Currents Assets | E35: =E32-E33 -> 16584 | F35: =F32-F33 -> 16961 | G35: =G32-G33 -> 17853 | H35: =H32-H33 -> 18731 | I35: =I32-I33 -> 25663 | J35: =J32-J33 -> 28517
B37: Invested Capital | E37: =E19+E35 -> 18490 | F37: =F19+F35 -> 18425 | G37: =G19+G35 -> 19414 | H37: =H19+H35 -> 19736 | I37: =I19+I35 -> 23245 | J37: =J19+J35 -> 26290
B38: EBIT | E38: ='Historical Financial'!C18-'Historical Financial'!C21 -> 1192.8 | F38: ='Historical Financial'!D18-'Historical Financial'!D21 -> 1592.01 | G38: ='Historical Financial'!E18-'Historical Financial'!E21 -> 1580.51 | H38: ='Historical Financial'!F18-'Historical Financial'!F21 -> 1631.57 | I38: ='Historical Financial'!G18-'Historical Financial'!G21 -> 2328.6 | J38: ='Historical Financial'!H18-'Historical Financial'!H21 -> 2710.48
B40: ROIC | E40: =E38/E37 -> 0.064510546 | F40: =F38/F37 -> 0.086404885 | G40: =G38/G37 -> 0.081410838 | H40: =H38/H37 -> 0.082669741 | I40: =I38/I37 -> 0.10017638 | J40: =J38/J37 -> 0.10309928
B42: Calculation of Reinvestment Rate | E42: =E2 -> 43921 | F42: =F2 -> 44286 | G42: =G2 -> 44651 | H42: =H2 -> 45016 | I42: =I2 -> 45382 | J42: =J2 -> 45747
B44: Net Capex | E44: =SUM('Cashflow Data '!G12:G13) -> -151 | F44: =SUM('Cashflow Data '!H12:H13) -> -179 | G44: =SUM('Cashflow Data '!I12:I13) -> -246 | H44: =SUM('Cashflow Data '!J12:J13) -> -140 | I44: =SUM('Cashflow Data '!K12:K13) -> -311 | J44: =SUM('Cashflow Data '!L12:L13) -> -415
B45: Change in working capital | F45: =F19-E19 -> -442 | G45: =G19-F19 -> 97 | H45: =H19-G19 -> -556 | I45: =I19-H19 -> -3423 | J45: =J19-I19 -> 191
B47: EBIT | E47: =E38 -> 1192.8 | F47: =F38 -> 1592.01 | G47: =G38 -> 1580.51 | H47: =H38 -> 1631.57 | I47: =I38 -> 2328.6 | J47: =J38 -> 2710.48
B48: Marginal Tax | E48: 0.3 | F48: 0.3 | G48: 0.3 | H48: 0.3 | I48: 0.3 | J48: 0.3
B49: EBIT(1-Tax) | E49: =E47*(1-E48) -> 834.96 | F49: =F47*(1-F48) -> 1114.407 | G49: =G47*(1-G48) -> 1106.357 | H49: =H47*(1-H48) -> 1142.099 | I49: =I47*(1-I48) -> 1630.02 | J49: =J47*(1-J48) -> 1897.336
B51: Reinvestment | F51: =F44+F45 -> -621 | G51: =G44+G45 -> -149 | H51: =H44+H45 -> -696 | I51: =I44+I45 -> -3734 | J51: =J44+J45 -> -224
B52: Reinvestment Rate | F52: =F51/F49 -> -0.55724704 | G52: =G51/G49 -> -0.13467624 | H52: =H51/H49 -> -0.60940426 | I52: =I51/I49 -> -2.2907694 | J52: =J51/J49 -> -0.11806027
H54: 5year Average | J54: =AVERAGE(F52:J52) -> -0.74203145
H55: 5years Median | J55: =MEDIAN(F52:J52) -> -0.55724704
B57: Calculation of Growth Rate | E57: =E42 -> 43921 | F57: =F42 -> 44286 | G57: =G42 -> 44651 | H57: =H42 -> 45016 | I57: =I42 -> 45382 | J57: =J42 -> 45747
B59: Reinvestment Rate | F59: =F52 -> -0.55724704 | G59: =G52 -> -0.13467624 | H59: =H52 -> -0.60940426 | I59: =I52 -> -2.2907694 | J59: =J52 -> -0.11806027
B60: ROIC | F60: =F40 -> 0.086404885 | G60: =G40 -> 0.081410838 | H60: =H40 -> 0.082669741 | I60: =I40 -> 0.10017638 | J60: =J40 -> 0.10309928
B61: Intrinsic Growth | F61: =F59*F60 -> -0.048148866 | G61: =G59*G60 -> -0.010964105 | H61: =H59*H60 -> -0.050379292 | I61: =I59*I60 -> -0.22948099 | J61: =J59*J60 -> -0.012171928
H63: 5year Average | J63: =AVERAGE(F61:J61) -> -0.070229037
H64: 5years Median | J64: =MEDIAN(F61:J61) -> -0.048148866

Sheet DCF Model 
B2: Calculation of PV of FCFF | E2: ='[1]Intrisic Growth'!I4 -> 45717 | F2: =E2+365 -> 46082 | G2: =F2+365 -> 46447 | H2: =G2+366 -> 46813 | I2: =H2+365 -> 47178 | J2: =I2+365 -> 47543
B4: EBIT | E4: ='Internsic Growth'!J47 -> 2710.48 | F4: =E4*(1+$E$15) -> 2579.9735 | G4: =F4*(1+$E$15) -> 2455.7507 | H4: =G4*(1+$E$15) -> 2337.5091 | I4: =H4*(1+$E$15) -> 2224.9606 | J4: =I4*(1+$E$15) -> 2117.8313
B5: Tax | E5: 0.25 | F5: 0.25 | G5: 0.25 | H5: 0.25 | I5: 0.25 | J5: 0.25
B6: EBIT(1-Tax) | E6: =E4*(1-E5) -> 2032.86 | F6: =F4*(1-F5) -> 1934.9801 | G6: =G4*(1-G5) -> 1841.813 | H6: =H4*(1-H5) -> 1753.1318 | I6: =I4*(1-I5) -> 1668.7205 | J6: =J4*(1-J5) -> 1588.3735
B7: Less Reinvestment Rate | E7: ='Internsic Growth'!$J$55 -> -0.55724704 | F7: ='Internsic Growth'!$J$55 -> -0.55724704 | G7: ='Internsic Growth'!$J$55 -> -0.55724704 | H7: ='Internsic Growth'!$J$55 -> -0.55724704 | I7: ='Internsic Growth'!$J$55 -> -0.55724704 | J7: ='Internsic Growth'!$J$55 -> -0.55724704
B8: Free Cash Flow to Firm(FCFF) | E8: =E6*(1-E7) -> 3165.6652 | F8: =F6*(1-F7) -> 3013.242 | G8: =G6*(1-G7) -> 2868.1578 | H8: =H6*(1-H7) -> 2730.0593 | I8: =I6*(1-I7) -> 2598.61 | J8: =J6*(1-J7) -> 2473.4899
B10: Mid Year Convention | F10: 0.5 | G10: =F10+1 -> 1.5 | H10: =G10+1 -> 2.5 | I10: =H10+1 -> 3.5 | J10: =I10+1 -> 4.5
B12: Discount Factor | F12: =1/(1+$E$17)^F10 -> 0.93933419 | G12: =1/(1+$E$17)^G10 -> 0.82882033 | H12: =1/(1+$E$17)^H10 -> 0.73130856 | I12: =1/(1+$E$17)^I10 -> 0.64526918 | J12: =1/(1+$E$17)^J10 -> 0.56935244
B13: PV of FCFF | F13: =F8*F12 -> 2830.4413 | G13: =G8*G12 -> 2377.1875 | H13: =H8*H12 -> 1996.5157 | I13: =I8*I12 -> 1676.803 | J13: =J8*J12 -> 1408.2875
B15: Expected Growth | E15: ='Internsic Growth'!J64 -> -0.048148866
B16: Terminal Growth | E16: 0.07
B17: WACC | E17: =WACC!K39 -> 0.13333875
B19: Calculation of Terminal Value
B21: FCFF(n+1) | E21: =J8*(1+E16) -> 2646.6342
B22: Terminal Growth | E22: =E16 -> 0.07
B23: WACC | E23: =E17 -> 0.13333875
B24: Terminal Value | E24: =E21/(E23-E22) -> 41785.389
B26: Calculation of Equity Value
B28: PV of FCFF | E28: =SUM(F13:J13) -> 10289.235
B29: PV of Terminal Value | E29: =E24/(1+E23)^5 -> 22347.336
B30: Value of Operating Assets | E30: =E28+E29 -> 32636.571
B31: Add: Cash | E31: ='Data Sheet'!K69 -> 2817.86
B32: Less: Debt | E32: =SUM('Raw Financial '!M8:M9) -> 1849
B33: Value of the Equity | E33: =E30+E31-E32 -> 33605.431
B34: Number of Equity Share | E34: ='Data Sheet'!B6 -> 98.946939
B35: Equity Value per Share | E35: =E33/E34 -> 339.63083
B37: Share Price | E37: 1050.2
B38: Discount/Premium | E38: =E37/E35-1 -> 2.092181
